Workbook
Name DeliveryDays: Overall!$B$5
Name WorkingDaysPerMonth: Overall!$B$6
Name DeliveryMonths: Overall!$B$7
Name HoursPerMonth: Overall!$B$8
Name ProjectStart: Overall!$B$9
Name SprintDays: Overall!$B$10
Name HorizonYears: Overall!$B$11
Name CostEscalation: Overall!$B$12
Name HorizonFactor: Overall!$B$13
Name Contingency: Overall!$B$14
Name FxRate: Overall!$B$15
Name ClaudeFxRate: Overall!$B$16
Name LastActual: Sprints!$C$3

Sheet Overall
A1: Falcon Portal cost estimate (synthetic sample)
A2: All costs in USD. Cloud: Azure retail list prices in uaenorth fetched 2026-09-28, no discounts or reservations. Blue cells are inputs; black cells are formulas; green cells link to other sheets.
A3: Inputs
A4: Input | B4: Value
A5: Days of delivery (working days) | B5: 84
A6: Working days per month | B6: 21
A7: Months of delivery | B7: =DeliveryDays/WorkingDaysPerMonth
A8: Hours per month (always-on services) | B8: 730
A9: Delivery start date (optional; dates the epics and sprints) | B9: 46083
A10: Working days per sprint | B10: 10
A11: Years of run after go-live (3 to 5) | B11: 5
A12: Yearly increase in run costs | B12: 0.03
A13: Run years, with the yearly increase | B13: =IF(CostEscalation=0,HorizonYears,((1+CostEscalation)^HorizonYears-1)/CostEscalation)
A14: Contingency | B14: 0.1
A15: Exchange rate (1 USD = x USD) | B15: 1
A16: Exchange rate for Claude prices (1 USD = x USD) | B16: 1
A18: Delivery team (build)
A19: Role | B19: Day rate (USD) | C19: Employees | D19: Days on delivery | E19: Allocation | F19: Mandays | G19: Cost (USD) | H19: Cited from
A20: Project Manager | B20: =VLOOKUP(A20,'Rate Card'!$A$5:$B$50,2,FALSE) | C20: 1 | D20: =DeliveryDays | E20: 0.5 | F20: =C20*D20*E20 | G20: =F20*B20 | H20: owner: Delivery Manager, 2026-09-28
A21: Solution Architect | B21: =VLOOKUP(A21,'Rate Card'!$A$5:$B$50,2,FALSE) | C21: 1 | D21: 20 | E21: 1 | F21: =C21*D21*E21 | G21: =F21*B21 | H21: owner: Delivery Manager, 2026-09-28
A22: Tech Lead | B22: =VLOOKUP(A22,'Rate Card'!$A$5:$B$50,2,FALSE) | C22: 1 | D22: =DeliveryDays | E22: 1 | F22: =C22*D22*E22 | G22: =F22*B22 | H22: _bmad-output/planning-artifacts/architecture/falcon/ARCHITECTURE-SPINE.md AD-1
A23: Developer | B23: =VLOOKUP(A23,'Rate Card'!$A$5:$B$50,2,FALSE) | C23: 3 | D23: =DeliveryDays | E23: 1 | F23: =C23*D23*E23 | G23: =F23*B23 | H23: _bmad-output/specs/SPEC.md 3 Users
A24: QA Engineer | B24: =VLOOKUP(A24,'Rate Card'!$A$5:$B$50,2,FALSE) | C24: 1 | D24: =DeliveryDays | E24: 1 | F24: =C24*D24*E24 | G24: =F24*B24 | H24: owner: Delivery Manager, 2026-09-28
A25: DevOps Engineer | B25: =VLOOKUP(A25,'Rate Card'!$A$5:$B$50,2,FALSE) | C25: 1 | D25: =DeliveryDays | E25: 0.5 | F25: =C25*D25*E25 | G25: =F25*B25 | H25: _bmad-output/planning-artifacts/architecture/falcon/ARCHITECTURE-SPINE.md AD-1
B26: =IF(A26="","",VLOOKUP(A26,'Rate Card'!$A$5:$B$50,2,FALSE)) | F26: =IF(A26="","",C26*D26*E26) | G26: =IF(A26="","",F26*B26)
B27: =IF(A27="","",VLOOKUP(A27,'Rate Card'!$A$5:$B$50,2,FALSE)) | F27: =IF(A27="","",C27*D27*E27) | G27: =IF(A27="","",F27*B27)
B28: =IF(A28="","",VLOOKUP(A28,'Rate Card'!$A$5:$B$50,2,FALSE)) | F28: =IF(A28="","",C28*D28*E28) | G28: =IF(A28="","",F28*B28)
A29: Total | C29: =SUM(C20:C28) | F29: =SUM(F20:F28) | G29: =SUM(G20:G28)
A31: Run support (OPEX): IT support and maintenance after go-live
A32: Role | B32: Day rate (USD) | C32: Mandays per year | D32: Cost per year (USD) | E32: Cited from
A33: Developer | B33: =VLOOKUP(A33,'Rate Card'!$A$5:$B$50,2,FALSE) | C33: 60 | D33: =C33*B33 | E33: owner: Delivery Manager, 2026-09-28
A34: DevOps Engineer | B34: =VLOOKUP(A34,'Rate Card'!$A$5:$B$50,2,FALSE) | C34: 24 | D34: =C34*B34 | E34: owner: Delivery Manager, 2026-09-28
A35: QA Engineer | B35: =VLOOKUP(A35,'Rate Card'!$A$5:$B$50,2,FALSE) | C35: 12 | D35: =C35*B35 | E35: owner: Delivery Manager, 2026-09-28
B36: =IF(A36="","",VLOOKUP(A36,'Rate Card'!$A$5:$B$50,2,FALSE)) | D36: =IF(A36="","",C36*B36)
B37: =IF(A37="","",VLOOKUP(A37,'Rate Card'!$A$5:$B$50,2,FALSE)) | D37: =IF(A37="","",C37*B37)
B38: =IF(A38="","",VLOOKUP(A38,'Rate Card'!$A$5:$B$50,2,FALSE)) | D38: =IF(A38="","",C38*B38)
A39: Total | C39: =SUM(C33:C38) | D39: =SUM(D33:D38)
A41: Cost summary
A42: Item | B42: Monthly (USD) | C42: Months in delivery | D42: Delivery cost (USD) | E42: Run months per year | F42: Run cost per year (USD) | G42: Run cost over the horizon (USD) | H42: Total (USD) | I42: From
A43: Dev environment | B43: ='Dev'!$I$13 | C43: =DeliveryMonths | D43: =B43*C43 | E43: 12 | F43: =B43*E43 | G43: =F43*HorizonFactor | H43: =D43+G43 | I43: Dev sheet
A44: Test environment | B44: ='Test'!$I$14 | C44: 2 | D44: =B44*C44 | E44: 12 | F44: =B44*E44 | G44: =F44*HorizonFactor | H44: =D44+G44 | I44: Test sheet
A45: Prod environment | B45: ='Prod'!$I$14 | C45: 1 | D45: =B45*C45 | E45: 12 | F45: =B45*E45 | G45: =F45*HorizonFactor | H45: =D45+G45 | I45: Prod sheet
A46: Delivery team | D46: =G29 | H46: =D46+G46 | I46: Delivery team table above
A47: Run support (OPEX) | F47: =D39 | G47: =F47*HorizonFactor | H47: =D47+G47 | I47: Run support table above
A48: Recurring run costs | F48: ='Run Costs'!$C$10 | G48: =F48*HorizonFactor | H48: =D48+G48 | I48: Run Costs sheet
A49: Other one-off costs | D49: ='Other Costs'!$C$10 | H49: =D49+G49 | I49: Other Costs sheet
A50: Subtotal | D50: =SUM(D43:D49) | F50: =SUM(F43:F49) | G50: =SUM(G43:G49) | H50: =SUM(H43:H49)
A51: Contingency | D51: =D50*Contingency | F51: =F50*Contingency | G51: =G50*Contingency | H51: =D51+G51
A52: Grand total | D52: =D50+D51 | F52: =F50+F51 | G52: =G50+G51 | H52: =H50+H51
A54: Memo: Claude API usage at API list prices (not in the totals: Claude Code was on a subscription) | D54: ='Claude Usage'!$I$8

Sheet Multi-Year
A1: Multi-year view
A2: In USD. Build is the delivery; each year after go-live carries the run costs, raised by the yearly increase, and the revenue given for it. Years past the horizon (Overall input) show zero. Contingency applies to every cost.
A4: Category | B4: Item | C4: Build | D4: Year 1 | E4: Year 2 | F4: Year 3 | G4: Year 4 | H4: Year 5 | I4: Total
A5: Revenue | B5: =IF('Revenue'!$B$5="","(spare revenue row)",'Revenue'!$B$5) | C5: 0 | D5: =IF(1<=HorizonYears,'Revenue'!D$5,0) | E5: =IF(2<=HorizonYears,'Revenue'!E$5,0) | F5: =IF(3<=HorizonYears,'Revenue'!F$5,0) | G5: =IF(4<=HorizonYears,'Revenue'!G$5,0) | H5: =IF(5<=HorizonYears,'Revenue'!H$5,0) | I5: =SUM(C5:H5)
A6: Revenue | B6: =IF('Revenue'!$B$6="","(spare revenue row)",'Revenue'!$B$6) | C6: 0 | D6: =IF(1<=HorizonYears,'Revenue'!D$6,0) | E6: =IF(2<=HorizonYears,'Revenue'!E$6,0) | F6: =IF(3<=HorizonYears,'Revenue'!F$6,0) | G6: =IF(4<=HorizonYears,'Revenue'!G$6,0) | H6: =IF(5<=HorizonYears,'Revenue'!H$6,0) | I6: =SUM(C6:H6)
A7: Revenue | B7: =IF('Revenue'!$B$7="","(spare revenue row)",'Revenue'!$B$7) | C7: 0 | D7: =IF(1<=HorizonYears,'Revenue'!D$7,0) | E7: =IF(2<=HorizonYears,'Revenue'!E$7,0) | F7: =IF(3<=HorizonYears,'Revenue'!F$7,0) | G7: =IF(4<=HorizonYears,'Revenue'!G$7,0) | H7: =IF(5<=HorizonYears,'Revenue'!H$7,0) | I7: =SUM(C7:H7)
A8: Revenue | B8: =IF('Revenue'!$B$8="","(spare revenue row)",'Revenue'!$B$8) | C8: 0 | D8: =IF(1<=HorizonYears,'Revenue'!D$8,0) | E8: =IF(2<=HorizonYears,'Revenue'!E$8,0) | F8: =IF(3<=HorizonYears,'Revenue'!F$8,0) | G8: =IF(4<=HorizonYears,'Revenue'!G$8,0) | H8: =IF(5<=HorizonYears,'Revenue'!H$8,0) | I8: =SUM(C8:H8)
A9: Cost | B9: Build: delivery team, environments during delivery, one-off costs | C9: ='Overall'!$D$50 | D9: 0 | E9: 0 | F9: 0 | G9: 0 | H9: 0 | I9: =SUM(C9:H9)
A10: Cost | B10: Dev environment (run) | C10: 0 | D10: =IF(1<=HorizonYears,'Overall'!$F$43*(1+CostEscalation)^0,0) | E10: =IF(2<=HorizonYears,'Overall'!$F$43*(1+CostEscalation)^1,0) | F10: =IF(3<=HorizonYears,'Overall'!$F$43*(1+CostEscalation)^2,0) | G10: =IF(4<=HorizonYears,'Overall'!$F$43*(1+CostEscalation)^3,0) | H10: =IF(5<=HorizonYears,'Overall'!$F$43*(1+CostEscalation)^4,0) | I10: =SUM(C10:H10)
A11: Cost | B11: Test environment (run) | C11: 0 | D11: =IF(1<=HorizonYears,'Overall'!$F$44*(1+CostEscalation)^0,0) | E11: =IF(2<=HorizonYears,'Overall'!$F$44*(1+CostEscalation)^1,0) | F11: =IF(3<=HorizonYears,'Overall'!$F$44*(1+CostEscalation)^2,0) | G11: =IF(4<=HorizonYears,'Overall'!$F$44*(1+CostEscalation)^3,0) | H11: =IF(5<=HorizonYears,'Overall'!$F$44*(1+CostEscalation)^4,0) | I11: =SUM(C11:H11)
A12: Cost | B12: Prod environment (run) | C12: 0 | D12: =IF(1<=HorizonYears,'Overall'!$F$45*(1+CostEscalation)^0,0) | E12: =IF(2<=HorizonYears,'Overall'!$F$45*(1+CostEscalation)^1,0) | F12: =IF(3<=HorizonYears,'Overall'!$F$45*(1+CostEscalation)^2,0) | G12: =IF(4<=HorizonYears,'Overall'!$F$45*(1+CostEscalation)^3,0) | H12: =IF(5<=HorizonYears,'Overall'!$F$45*(1+CostEscalation)^4,0) | I12: =SUM(C12:H12)
A13: Cost | B13: Run support (OPEX) | C13: 0 | D13: =IF(1<=HorizonYears,'Overall'!$F$47*(1+CostEscalation)^0,0) | E13: =IF(2<=HorizonYears,'Overall'!$F$47*(1+CostEscalation)^1,0) | F13: =IF(3<=HorizonYears,'Overall'!$F$47*(1+CostEscalation)^2,0) | G13: =IF(4<=HorizonYears,'Overall'!$F$47*(1+CostEscalation)^3,0) | H13: =IF(5<=HorizonYears,'Overall'!$F$47*(1+CostEscalation)^4,0) | I13: =SUM(C13:H13)
A14: Cost | B14: Recurring run costs | C14: 0 | D14: =IF(1<=HorizonYears,'Overall'!$F$48*(1+CostEscalation)^0,0) | E14: =IF(2<=HorizonYears,'Overall'!$F$48*(1+CostEscalation)^1,0) | F14: =IF(3<=HorizonYears,'Overall'!$F$48*(1+CostEscalation)^2,0) | G14: =IF(4<=HorizonYears,'Overall'!$F$48*(1+CostEscalation)^3,0) | H14: =IF(5<=HorizonYears,'Overall'!$F$48*(1+CostEscalation)^4,0) | I14: =SUM(C14:H14)
A15: Contingency | B15: Contingency on every cost | C15: =SUMIF($A$5:$A$14,"Cost",C5:C14)*Contingency | D15: =SUMIF($A$5:$A$14,"Cost",D5:D14)*Contingency | E15: =SUMIF($A$5:$A$14,"Cost",E5:E14)*Contingency | F15: =SUMIF($A$5:$A$14,"Cost",F5:F14)*Contingency | G15: =SUMIF($A$5:$A$14,"Cost",G5:G14)*Contingency | H15: =SUMIF($A$5:$A$14,"Cost",H5:H14)*Contingency | I15: =SUM(C15:H15)
A16: Total revenue | C16: =SUMIF($A$5:$A$15,"Revenue",C5:C15) | D16: =SUMIF($A$5:$A$15,"Revenue",D5:D15) | E16: =SUMIF($A$5:$A$15,"Revenue",E5:E15) | F16: =SUMIF($A$5:$A$15,"Revenue",F5:F15) | G16: =SUMIF($A$5:$A$15,"Revenue",G5:G15) | H16: =SUMIF($A$5:$A$15,"Revenue",H5:H15) | I16: =SUMIF($A$5:$A$15,"Revenue",I5:I15)
A17: Total costs | C17: =SUMIF($A$5:$A$15,"Cost",C5:C15)+SUMIF($A$5:$A$15,"Contingency",C5:C15) | D17: =SUMIF($A$5:$A$15,"Cost",D5:D15)+SUMIF($A$5:$A$15,"Contingency",D5:D15) | E17: =SUMIF($A$5:$A$15,"Cost",E5:E15)+SUMIF($A$5:$A$15,"Contingency",E5:E15) | F17: =SUMIF($A$5:$A$15,"Cost",F5:F15)+SUMIF($A$5:$A$15,"Contingency",F5:F15) | G17: =SUMIF($A$5:$A$15,"Cost",G5:G15)+SUMIF($A$5:$A$15,"Contingency",G5:G15) | H17: =SUMIF($A$5:$A$15,"Cost",H5:H15)+SUMIF($A$5:$A$15,"Contingency",H5:H15) | I17: =SUMIF($A$5:$A$15,"Cost",I5:I15)+SUMIF($A$5:$A$15,"Contingency",I5:I15)
A18: Net | C18: =C16-C17 | D18: =D16-D17 | E18: =E16-E17 | F18: =F16-F17 | G18: =G16-G17 | H18: =H16-H17 | I18: =I16-I17
A19: Cumulative net | C19: =C18 | D19: =C19+D18 | E19: =D19+E18 | F19: =E19+F18 | G19: =F19+G18 | H19: =G19+H18 | I19: =H19
A21: Payback | B21: =IF(C19>=0,"Build",IF(D19>=0,"Year 1",IF(E19>=0,"Year 2",IF(F19>=0,"Year 3",IF(G19>=0,"Year 4",IF(H19>=0,"Year 5","beyond the horizon"))))))
A22: Return on cost (net / costs) | B22: =IF(I17=0,"",I18/I17)

Sheet Epics
A1: Epics: deliverables, forecast and actual
A2: In USD. Forecast: each epic takes a share of the build in proportion to its planned working days (that share of the delivery team and of the environments during delivery), plus the one-off costs tagged to it and its Claude API budget; dates run the epics one after another from the delivery start date. Actual: enter or keep the actual start and end dates; actual working days, the Claude API actual from the ledger, and team and infra scaled by actual / planned days (same team and rates) unless you enter the timesheet team cost. Blue cells are inputs; add an epic in a spare row.
A4: Epic | B4: Name | C4: Deliverables | D4: Planned days | E4: Planned weeks | F4: Planned start | G4: Planned end | H4: Share of build | I4: Team mandays | J4: Team cost (USD) | K4: Infra cost (USD) | L4: Other costs (USD) | M4: Claude API budget (USD) | N4: Forecast total (USD) | O4: Actual start | P4: Actual end | Q4: Actual days | R4: Days variance | S4: Days variance % | T4: Claude API actual (USD) | U4: Actual team cost, timesheets (USD) | V4: Actual total (USD) | W4: Cost variance (USD) | X4: Cited from
A5: 1 | B5: Customer onboarding | C5: 1.1 Sign in with Entra ID 1.2 Start an application 1.3 Upload documents | D5: 40 | E5: =IF(D5="","",D5/5) | F5: =IF(OR(D5="",ProjectStart=""),"",ProjectStart) | G5: =IF(F5="","",WORKDAY(F5,D5-1)) | H5: =IF(D5="","",D5/SUM($D$5:$D$9)) | I5: =IF(D5="","",H5*'Overall'!$F$29) | J5: =IF(D5="","",H5*'Overall'!$G$29) | K5: =IF(D5="","",H5*('Overall'!$D$43+'Overall'!$D$44+'Overall'!$D$45)) | L5: =IF(A5="","",SUMIFS('Other Costs'!$C$5:$C$9,'Other Costs'!$F$5:$F$9,A5)) | M5: 150 | N5: =IF(D5="","",J5+K5+L5+N(M5)) | O5: 46083 | P5: 46132 | Q5: =IF(OR(D5="",O5="",P5=""),"",NETWORKDAYS(O5,P5)) | R5: =IF(Q5="","",Q5-D5) | S5: =IF(Q5="","",Q5/D5-1) | T5: =IF(A5="","",SUMIFS('Claude Usage Detail'!$P$5:$P$19,'Claude Usage Detail'!$C$5:$C$19,A5&".*")) | V5: =IF(Q5="","",IF(U5="",J5*Q5/D5,U5)+K5*Q5/D5+L5+N(T5)) | W5: =IF(V5="","",V5-N5) | X5: _bmad-output/planning-artifacts/epics.md Epic 1: Customer onboarding
A6: 2 | B6: Review and decision | C6: 2.1 Review queue 2.2 Approve or reject 2.3 Notify the customer | D6: 44 | E6: =IF(D6="","",D6/5) | F6: =IF(OR(D6="",ProjectStart=""),"",WORKDAY(G5,1)) | G6: =IF(F6="","",WORKDAY(F6,D6-1)) | H6: =IF(D6="","",D6/SUM($D$5:$D$9)) | I6: =IF(D6="","",H6*'Overall'!$F$29) | J6: =IF(D6="","",H6*'Overall'!$G$29) | K6: =IF(D6="","",H6*('Overall'!$D$43+'Overall'!$D$44+'Overall'!$D$45)) | L6: =IF(A6="","",SUMIFS('Other Costs'!$C$5:$C$9,'Other Costs'!$F$5:$F$9,A6)) | M6: 150 | N6: =IF(D6="","",J6+K6+L6+N(M6)) | O6: 46133 | P6: 46199 | Q6: =IF(OR(D6="",O6="",P6=""),"",NETWORKDAYS(O6,P6)) | R6: =IF(Q6="","",Q6-D6) | S6: =IF(Q6="","",Q6/D6-1) | T6: =IF(A6="","",SUMIFS('Claude Usage Detail'!$P$5:$P$19,'Claude Usage Detail'!$C$5:$C$19,A6&".*")) | V6: =IF(Q6="","",IF(U6="",J6*Q6/D6,U6)+K6*Q6/D6+L6+N(T6)) | W6: =IF(V6="","",V6-N6) | X6: _bmad-output/planning-artifacts/epics.md Epic 2: Review and decision
E7: =IF(D7="","",D7/5) | F7: =IF(OR(D7="",ProjectStart=""),"",WORKDAY(G6,1)) | G7: =IF(F7="","",WORKDAY(F7,D7-1)) | H7: =IF(D7="","",D7/SUM($D$5:$D$9)) | I7: =IF(D7="","",H7*'Overall'!$F$29) | J7: =IF(D7="","",H7*'Overall'!$G$29) | K7: =IF(D7="","",H7*('Overall'!$D$43+'Overall'!$D$44+'Overall'!$D$45)) | L7: =IF(A7="","",SUMIFS('Other Costs'!$C$5:$C$9,'Other Costs'!$F$5:$F$9,A7)) | N7: =IF(D7="","",J7+K7+L7+N(M7)) | Q7: =IF(OR(D7="",O7="",P7=""),"",NETWORKDAYS(O7,P7)) | R7: =IF(Q7="","",Q7-D7) | S7: =IF(Q7="","",Q7/D7-1) | T7: =IF(A7="","",SUMIFS('Claude Usage Detail'!$P$5:$P$19,'Claude Usage Detail'!$C$5:$C$19,A7&".*")) | V7: =IF(Q7="","",IF(U7="",J7*Q7/D7,U7)+K7*Q7/D7+L7+N(T7)) | W7: =IF(V7="","",V7-N7)
E8: =IF(D8="","",D8/5) | F8: =IF(OR(D8="",ProjectStart=""),"",WORKDAY(G7,1)) | G8: =IF(F8="","",WORKDAY(F8,D8-1)) | H8: =IF(D8="","",D8/SUM($D$5:$D$9)) | I8: =IF(D8="","",H8*'Overall'!$F$29) | J8: =IF(D8="","",H8*'Overall'!$G$29) | K8: =IF(D8="","",H8*('Overall'!$D$43+'Overall'!$D$44+'Overall'!$D$45)) | L8: =IF(A8="","",SUMIFS('Other Costs'!$C$5:$C$9,'Other Costs'!$F$5:$F$9,A8)) | N8: =IF(D8="","",J8+K8+L8+N(M8)) | Q8: =IF(OR(D8="",O8="",P8=""),"",NETWORKDAYS(O8,P8)) | R8: =IF(Q8="","",Q8-D8) | S8: =IF(Q8="","",Q8/D8-1) | T8: =IF(A8="","",SUMIFS('Claude Usage Detail'!$P$5:$P$19,'Claude Usage Detail'!$C$5:$C$19,A8&".*")) | V8: =IF(Q8="","",IF(U8="",J8*Q8/D8,U8)+K8*Q8/D8+L8+N(T8)) | W8: =IF(V8="","",V8-N8)
E9: =IF(D9="","",D9/5) | F9: =IF(OR(D9="",ProjectStart=""),"",WORKDAY(G8,1)) | G9: =IF(F9="","",WORKDAY(F9,D9-1)) | H9: =IF(D9="","",D9/SUM($D$5:$D$9)) | I9: =IF(D9="","",H9*'Overall'!$F$29) | J9: =IF(D9="","",H9*'Overall'!$G$29) | K9: =IF(D9="","",H9*('Overall'!$D$43+'Overall'!$D$44+'Overall'!$D$45)) | L9: =IF(A9="","",SUMIFS('Other Costs'!$C$5:$C$9,'Other Costs'!$F$5:$F$9,A9)) | N9: =IF(D9="","",J9+K9+L9+N(M9)) | Q9: =IF(OR(D9="",O9="",P9=""),"",NETWORKDAYS(O9,P9)) | R9: =IF(Q9="","",Q9-D9) | S9: =IF(Q9="","",Q9/D9-1) | T9: =IF(A9="","",SUMIFS('Claude Usage Detail'!$P$5:$P$19,'Claude Usage Detail'!$C$5:$C$19,A9&".*")) | V9: =IF(Q9="","",IF(U9="",J9*Q9/D9,U9)+K9*Q9/D9+L9+N(T9)) | W9: =IF(V9="","",V9-N9)
A10: Total | D10: =SUM(D5:D9) | I10: =SUM(I5:I9) | J10: =SUM(J5:J9) | K10: =SUM(K5:K9) | L10: =SUM(L5:L9) | M10: =SUM(M5:M9) | N10: =SUM(N5:N9) | Q10: =SUM(Q5:Q9) | R10: =SUM(R5:R9) | S10: =IF(Q10=0,"",Q10/SUMIFS(D5:D9,Q5:Q9,">0")-1) | T10: =SUM(T5:T9) | U10: =SUM(U5:U9) | V10: =SUM(V5:V9) | W10: =SUM(W5:W9)
A12: =IF(D10=DeliveryDays,"The planned epics add up to the days of delivery.","The planned epics add up to "&D10&" working days; the days of delivery input is "&DeliveryDays&". Costs are shared by planned epic days either way.")

Sheet Sprints
A1: Sprints: forecast and actual
A2: In USD. Every sprint is a timebox of the Overall input 'Working days per sprint' from the delivery start date. Forecast: the sprint's planned working days (the days of delivery, sprint by sprint) at the delivery team's and the environments' daily cost, plus any Claude API budget. Actual, up to the last actual activity (the latest completed story or day of Claude usage): the days worked in the sprint, the stories completed, the Claude API cost on its days, and the team at the days worked unless timesheets are entered. Sprints past the plan appear when work ran over. Blue cells are inputs.
A3: Last actual activity | C3: =IF(MAX(MAXIFS('Project Timeline'!$F$5:$F$20,'Project Timeline'!$A$5:$A$20,"story"),MAX('Claude Usage Daily'!$A$5:$A$233))=0,"",MAX(MAXIFS('Project Timeline'!$F$5:$F$20,'Project Timeline'!$A$5:$A$20,"story"),MAX('Claude Usage Daily'!$A$5:$A$233)))
A4: Sprint | B4: Start | C4: End | D4: Planned days | E4: Planned stories | F4: Team cost (USD) | G4: Infra cost (USD) | H4: Claude API budget (USD) | I4: Forecast total (USD) | J4: Days worked | K4: Stories done | L4: Stories done (list) | M4: Claude API actual (USD) | N4: Actual team cost, timesheets (USD) | O4: Actual total (USD) | P4: Cost variance (USD)
A5: 1 | B5: =IF(OR(D5="",ProjectStart=""),"",WORKDAY(ProjectStart,(1-1)*SprintDays)) | C5: =IF(B5="","",WORKDAY(B5,SprintDays-1)) | D5: =IF(OR(MIN(SprintDays,MAX(0,DeliveryDays-(1-1)*SprintDays))>0,AND(ProjectStart<>"",LastActual<>"",WORKDAY(ProjectStart,(1-1)*SprintDays)<=N(LastActual))),MIN(SprintDays,MAX(0,DeliveryDays-(1-1)*SprintDays)),"") | E5: 1.1 Sign in with Entra ID | F5: =IF(D5="","",D5*'Overall'!$G$29/DeliveryDays) | G5: =IF(D5="","",D5*('Overall'!$D$43+'Overall'!$D$44+'Overall'!$D$45)/DeliveryDays) | I5: =IF(D5="","",F5+G5+N(H5)) | J5: =IF(OR(B5="",LastActual="",B5>N(LastActual)),"",NETWORKDAYS(B5,MIN(C5,LastActual))) | K5: =IF(J5="","",COUNTIFS('Project Timeline'!$A$5:$A$20,"story",'Project Timeline'!$F$5:$F$20,">="&B5,'Project Timeline'!$F$5:$F$20,"<="&C5)) | M5: =IF(J5="","",SUMIFS('Claude Usage Daily'!$O$5:$O$233,'Claude Usage Daily'!$A$5:$A$233,">="&B5,'Claude Usage Daily'!$A$5:$A$233,"<="&C5)) | O5: =IF(J5="","",IF(N5="",J5*'Overall'!$G$29/DeliveryDays,N5)+J5*('Overall'!$D$43+'Overall'!$D$44+'Overall'!$D$45)/DeliveryDays+N(M5)) | P5: =IF(O5="","",O5-N(I5))
A6: 2 | B6: =IF(OR(D6="",ProjectStart=""),"",WORKDAY(ProjectStart,(2-1)*SprintDays)) | C6: =IF(B6="","",WORKDAY(B6,SprintDays-1)) | D6: =IF(OR(MIN(SprintDays,MAX(0,DeliveryDays-(2-1)*SprintDays))>0,AND(ProjectStart<>"",LastActual<>"",WORKDAY(ProjectStart,(2-1)*SprintDays)<=N(LastActual))),MIN(SprintDays,MAX(0,DeliveryDays-(2-1)*SprintDays)),"") | E6: 1.2 Start an application | F6: =IF(D6="","",D6*'Overall'!$G$29/DeliveryDays) | G6: =IF(D6="","",D6*('Overall'!$D$43+'Overall'!$D$44+'Overall'!$D$45)/DeliveryDays) | I6: =IF(D6="","",F6+G6+N(H6)) | J6: =IF(OR(B6="",LastActual="",B6>N(LastActual)),"",NETWORKDAYS(B6,MIN(C6,LastActual))) | K6: =IF(J6="","",COUNTIFS('Project Timeline'!$A$5:$A$20,"story",'Project Timeline'!$F$5:$F$20,">="&B6,'Project Timeline'!$F$5:$F$20,"<="&C6)) | L6: 1-1-sign-in | M6: =IF(J6="","",SUMIFS('Claude Usage Daily'!$O$5:$O$233,'Claude Usage Daily'!$A$5:$A$233,">="&B6,'Claude Usage Daily'!$A$5:$A$233,"<="&C6)) | O6: =IF(J6="","",IF(N6="",J6*'Overall'!$G$29/DeliveryDays,N6)+J6*('Overall'!$D$43+'Overall'!$D$44+'Overall'!$D$45)/DeliveryDays+N(M6)) | P6: =IF(O6="","",O6-N(I6))
A7: 3 | B7: =IF(OR(D7="",ProjectStart=""),"",WORKDAY(ProjectStart,(3-1)*SprintDays)) | C7: =IF(B7="","",WORKDAY(B7,SprintDays-1)) | D7: =IF(OR(MIN(SprintDays,MAX(0,DeliveryDays-(3-1)*SprintDays))>0,AND(ProjectStart<>"",LastActual<>"",WORKDAY(ProjectStart,(3-1)*SprintDays)<=N(LastActual))),MIN(SprintDays,MAX(0,DeliveryDays-(3-1)*SprintDays)),"") | E7: 1.2 Start an application 1.3 Upload documents | F7: =IF(D7="","",D7*'Overall'!$G$29/DeliveryDays) | G7: =IF(D7="","",D7*('Overall'!$D$43+'Overall'!$D$44+'Overall'!$D$45)/DeliveryDays) | I7: =IF(D7="","",F7+G7+N(H7)) | J7: =IF(OR(B7="",LastActual="",B7>N(LastActual)),"",NETWORKDAYS(B7,MIN(C7,LastActual))) | K7: =IF(J7="","",COUNTIFS('Project Timeline'!$A$5:$A$20,"story",'Project Timeline'!$F$5:$F$20,">="&B7,'Project Timeline'!$F$5:$F$20,"<="&C7)) | L7: 1-2-start-application | M7: =IF(J7="","",SUMIFS('Claude Usage Daily'!$O$5:$O$233,'Claude Usage Daily'!$A$5:$A$233,">="&B7,'Claude Usage Daily'!$A$5:$A$233,"<="&C7)) | O7: =IF(J7="","",IF(N7="",J7*'Overall'!$G$29/DeliveryDays,N7)+J7*('Overall'!$D$43+'Overall'!$D$44+'Overall'!$D$45)/DeliveryDays+N(M7)) | P7: =IF(O7="","",O7-N(I7))
A8: 4 | B8: =IF(OR(D8="",ProjectStart=""),"",WORKDAY(ProjectStart,(4-1)*SprintDays)) | C8: =IF(B8="","",WORKDAY(B8,SprintDays-1)) | D8: =IF(OR(MIN(SprintDays,MAX(0,DeliveryDays-(4-1)*SprintDays))>0,AND(ProjectStart<>"",LastActual<>"",WORKDAY(ProjectStart,(4-1)*SprintDays)<=N(LastActual))),MIN(SprintDays,MAX(0,DeliveryDays-(4-1)*SprintDays)),"") | E8: 1.3 Upload documents | F8: =IF(D8="","",D8*'Overall'!$G$29/DeliveryDays) | G8: =IF(D8="","",D8*('Overall'!$D$43+'Overall'!$D$44+'Overall'!$D$45)/DeliveryDays) | I8: =IF(D8="","",F8+G8+N(H8)) | J8: =IF(OR(B8="",LastActual="",B8>N(LastActual)),"",NETWORKDAYS(B8,MIN(C8,LastActual))) | K8: =IF(J8="","",COUNTIFS('Project Timeline'!$A$5:$A$20,"story",'Project Timeline'!$F$5:$F$20,">="&B8,'Project Timeline'!$F$5:$F$20,"<="&C8)) | L8: 1-3-upload-documents | M8: =IF(J8="","",SUMIFS('Claude Usage Daily'!$O$5:$O$233,'Claude Usage Daily'!$A$5:$A$233,">="&B8,'Claude Usage Daily'!$A$5:$A$233,"<="&C8)) | O8: =IF(J8="","",IF(N8="",J8*'Overall'!$G$29/DeliveryDays,N8)+J8*('Overall'!$D$43+'Overall'!$D$44+'Overall'!$D$45)/DeliveryDays+N(M8)) | P8: =IF(O8="","",O8-N(I8))
A9: 5 | B9: =IF(OR(D9="",ProjectStart=""),"",WORKDAY(ProjectStart,(5-1)*SprintDays)) | C9: =IF(B9="","",WORKDAY(B9,SprintDays-1)) | D9: =IF(OR(MIN(SprintDays,MAX(0,DeliveryDays-(5-1)*SprintDays))>0,AND(ProjectStart<>"",LastActual<>"",WORKDAY(ProjectStart,(5-1)*SprintDays)<=N(LastActual))),MIN(SprintDays,MAX(0,DeliveryDays-(5-1)*SprintDays)),"") | E9: 2.1 Review queue | F9: =IF(D9="","",D9*'Overall'!$G$29/DeliveryDays) | G9: =IF(D9="","",D9*('Overall'!$D$43+'Overall'!$D$44+'Overall'!$D$45)/DeliveryDays) | I9: =IF(D9="","",F9+G9+N(H9)) | J9: =IF(OR(B9="",LastActual="",B9>N(LastActual)),"",NETWORKDAYS(B9,MIN(C9,LastActual))) | K9: =IF(J9="","",COUNTIFS('Project Timeline'!$A$5:$A$20,"story",'Project Timeline'!$F$5:$F$20,">="&B9,'Project Timeline'!$F$5:$F$20,"<="&C9)) | M9: =IF(J9="","",SUMIFS('Claude Usage Daily'!$O$5:$O$233,'Claude Usage Daily'!$A$5:$A$233,">="&B9,'Claude Usage Daily'!$A$5:$A$233,"<="&C9)) | O9: =IF(J9="","",IF(N9="",J9*'Overall'!$G$29/DeliveryDays,N9)+J9*('Overall'!$D$43+'Overall'!$D$44+'Overall'!$D$45)/DeliveryDays+N(M9)) | P9: =IF(O9="","",O9-N(I9))
A10: 6 | B10: =IF(OR(D10="",ProjectStart=""),"",WORKDAY(ProjectStart,(6-1)*SprintDays)) | C10: =IF(B10="","",WORKDAY(B10,SprintDays-1)) | D10: =IF(OR(MIN(SprintDays,MAX(0,DeliveryDays-(6-1)*SprintDays))>0,AND(ProjectStart<>"",LastActual<>"",WORKDAY(ProjectStart,(6-1)*SprintDays)<=N(LastActual))),MIN(SprintDays,MAX(0,DeliveryDays-(6-1)*SprintDays)),"") | E10: 2.1 Review queue 2.2 Approve or reject | F10: =IF(D10="","",D10*'Overall'!$G$29/DeliveryDays) | G10: =IF(D10="","",D10*('Overall'!$D$43+'Overall'!$D$44+'Overall'!$D$45)/DeliveryDays) | I10: =IF(D10="","",F10+G10+N(H10)) | J10: =IF(OR(B10="",LastActual="",B10>N(LastActual)),"",NETWORKDAYS(B10,MIN(C10,LastActual))) | K10: =IF(J10="","",COUNTIFS('Project Timeline'!$A$5:$A$20,"story",'Project Timeline'!$F$5:$F$20,">="&B10,'Project Timeline'!$F$5:$F$20,"<="&C10)) | L10: 2-1-review-queue | M10: =IF(J10="","",SUMIFS('Claude Usage Daily'!$O$5:$O$233,'Claude Usage Daily'!$A$5:$A$233,">="&B10,'Claude Usage Daily'!$A$5:$A$233,"<="&C10)) | O10: =IF(J10="","",IF(N10="",J10*'Overall'!$G$29/DeliveryDays,N10)+J10*('Overall'!$D$43+'Overall'!$D$44+'Overall'!$D$45)/DeliveryDays+N(M10)) | P10: =IF(O10="","",O10-N(I10))
A11: 7 | B11: =IF(OR(D11="",ProjectStart=""),"",WORKDAY(ProjectStart,(7-1)*SprintDays)) | C11: =IF(B11="","",WORKDAY(B11,SprintDays-1)) | D11: =IF(OR(MIN(SprintDays,MAX(0,DeliveryDays-(7-1)*SprintDays))>0,AND(ProjectStart<>"",LastActual<>"",WORKDAY(ProjectStart,(7-1)*SprintDays)<=N(LastActual))),MIN(SprintDays,MAX(0,DeliveryDays-(7-1)*SprintDays)),"") | E11: 2.2 Approve or reject | F11: =IF(D11="","",D11*'Overall'!$G$29/DeliveryDays) | G11: =IF(D11="","",D11*('Overall'!$D$43+'Overall'!$D$44+'Overall'!$D$45)/DeliveryDays) | I11: =IF(D11="","",F11+G11+N(H11)) | J11: =IF(OR(B11="",LastActual="",B11>N(LastActual)),"",NETWORKDAYS(B11,MIN(C11,LastActual))) | K11: =IF(J11="","",COUNTIFS('Project Timeline'!$A$5:$A$20,"story",'Project Timeline'!$F$5:$F$20,">="&B11,'Project Timeline'!$F$5:$F$20,"<="&C11)) | L11: 2-2-approve-or-reject | M11: =IF(J11="","",SUMIFS('Claude Usage Daily'!$O$5:$O$233,'Claude Usage Daily'!$A$5:$A$233,">="&B11,'Claude Usage Daily'!$A$5:$A$233,"<="&C11)) | O11: =IF(J11="","",IF(N11="",J11*'Overall'!$G$29/DeliveryDays,N11)+J11*('Overall'!$D$43+'Overall'!$D$44+'Overall'!$D$45)/DeliveryDays+N(M11)) | P11: =IF(O11="","",O11-N(I11))
A12: 8 | B12: =IF(OR(D12="",ProjectStart=""),"",WORKDAY(ProjectStart,(8-1)*SprintDays)) | C12: =IF(B12="","",WORKDAY(B12,SprintDays-1)) | D12: =IF(OR(MIN(SprintDays,MAX(0,DeliveryDays-(8-1)*SprintDays))>0,AND(ProjectStart<>"",LastActual<>"",WORKDAY(ProjectStart,(8-1)*SprintDays)<=N(LastActual))),MIN(SprintDays,MAX(0,DeliveryDays-(8-1)*SprintDays)),"") | E12: 2.3 Notify the customer | F12: =IF(D12="","",D12*'Overall'!$G$29/DeliveryDays) | G12: =IF(D12="","",D12*('Overall'!$D$43+'Overall'!$D$44+'Overall'!$D$45)/DeliveryDays) | I12: =IF(D12="","",F12+G12+N(H12)) | J12: =IF(OR(B12="",LastActual="",B12>N(LastActual)),"",NETWORKDAYS(B12,MIN(C12,LastActual))) | K12: =IF(J12="","",COUNTIFS('Project Timeline'!$A$5:$A$20,"story",'Project Timeline'!$F$5:$F$20,">="&B12,'Project Timeline'!$F$5:$F$20,"<="&C12)) | M12: =IF(J12="","",SUMIFS('Claude Usage Daily'!$O$5:$O$233,'Claude Usage Daily'!$A$5:$A$233,">="&B12,'Claude Usage Daily'!$A$5:$A$233,"<="&C12)) | O12: =IF(J12="","",IF(N12="",J12*'Overall'!$G$29/DeliveryDays,N12)+J12*('Overall'!$D$43+'Overall'!$D$44+'Overall'!$D$45)/DeliveryDays+N(M12)) | P12: =IF(O12="","",O12-N(I12))
A13: 9 | B13: =IF(OR(D13="",ProjectStart=""),"",WORKDAY(ProjectStart,(9-1)*SprintDays)) | C13: =IF(B13="","",WORKDAY(B13,SprintDays-1)) | D13: =IF(OR(MIN(SprintDays,MAX(0,DeliveryDays-(9-1)*SprintDays))>0,AND(ProjectStart<>"",LastActual<>"",WORKDAY(ProjectStart,(9-1)*SprintDays)<=N(LastActual))),MIN(SprintDays,MAX(0,DeliveryDays-(9-1)*SprintDays)),"") | E13: 2.3 Notify the customer | F13: =IF(D13="","",D13*'Overall'!$G$29/DeliveryDays) | G13: =IF(D13="","",D13*('Overall'!$D$43+'Overall'!$D$44+'Overall'!$D$45)/DeliveryDays) | I13: =IF(D13="","",F13+G13+N(H13)) | J13: =IF(OR(B13="",LastActual="",B13>N(LastActual)),"",NETWORKDAYS(B13,MIN(C13,LastActual))) | K13: =IF(J13="","",COUNTIFS('Project Timeline'!$A$5:$A$20,"story",'Project Timeline'!$F$5:$F$20,">="&B13,'Project Timeline'!$F$5:$F$20,"<="&C13)) | L13: 2-3-notify-customer | M13: =IF(J13="","",SUMIFS('Claude Usage Daily'!$O$5:$O$233,'Claude Usage Daily'!$A$5:$A$233,">="&B13,'Claude Usage Daily'!$A$5:$A$233,"<="&C13)) | O13: =IF(J13="","",IF(N13="",J13*'Overall'!$G$29/DeliveryDays,N13)+J13*('Overall'!$D$43+'Overall'!$D$44+'Overall'!$D$45)/DeliveryDays+N(M13)) | P13: =IF(O13="","",O13-N(I13))
A14: 10 | B14: =IF(OR(D14="",ProjectStart=""),"",WORKDAY(ProjectStart,(10-1)*SprintDays)) | C14: =IF(B14="","",WORKDAY(B14,SprintDays-1)) | D14: =IF(OR(MIN(SprintDays,MAX(0,DeliveryDays-(10-1)*SprintDays))>0,AND(ProjectStart<>"",LastActual<>"",WORKDAY(ProjectStart,(10-1)*SprintDays)<=N(LastActual))),MIN(SprintDays,MAX(0,DeliveryDays-(10-1)*SprintDays)),"") | F14: =IF(D14="","",D14*'Overall'!$G$29/DeliveryDays) | G14: =IF(D14="","",D14*('Overall'!$D$43+'Overall'!$D$44+'Overall'!$D$45)/DeliveryDays) | I14: =IF(D14="","",F14+G14+N(H14)) | J14: =IF(OR(B14="",LastActual="",B14>N(LastActual)),"",NETWORKDAYS(B14,MIN(C14,LastActual))) | K14: =IF(J14="","",COUNTIFS('Project Timeline'!$A$5:$A$20,"story",'Project Timeline'!$F$5:$F$20,">="&B14,'Project Timeline'!$F$5:$F$20,"<="&C14)) | M14: =IF(J14="","",SUMIFS('Claude Usage Daily'!$O$5:$O$233,'Claude Usage Daily'!$A$5:$A$233,">="&B14,'Claude Usage Daily'!$A$5:$A$233,"<="&C14)) | O14: =IF(J14="","",IF(N14="",J14*'Overall'!$G$29/DeliveryDays,N14)+J14*('Overall'!$D$43+'Overall'!$D$44+'Overall'!$D$45)/DeliveryDays+N(M14)) | P14: =IF(O14="","",O14-N(I14))
A15: 11 | B15: =IF(OR(D15="",ProjectStart=""),"",WORKDAY(ProjectStart,(11-1)*SprintDays)) | C15: =IF(B15="","",WORKDAY(B15,SprintDays-1)) | D15: =IF(OR(MIN(SprintDays,MAX(0,DeliveryDays-(11-1)*SprintDays))>0,AND(ProjectStart<>"",LastActual<>"",WORKDAY(ProjectStart,(11-1)*SprintDays)<=N(LastActual))),MIN(SprintDays,MAX(0,DeliveryDays-(11-1)*SprintDays)),"") | F15: =IF(D15="","",D15*'Overall'!$G$29/DeliveryDays) | G15: =IF(D15="","",D15*('Overall'!$D$43+'Overall'!$D$44+'Overall'!$D$45)/DeliveryDays) | I15: =IF(D15="","",F15+G15+N(H15)) | J15: =IF(OR(B15="",LastActual="",B15>N(LastActual)),"",NETWORKDAYS(B15,MIN(C15,LastActual))) | K15: =IF(J15="","",COUNTIFS('Project Timeline'!$A$5:$A$20,"story",'Project Timeline'!$F$5:$F$20,">="&B15,'Project Timeline'!$F$5:$F$20,"<="&C15)) | M15: =IF(J15="","",SUMIFS('Claude Usage Daily'!$O$5:$O$233,'Claude Usage Daily'!$A$5:$A$233,">="&B15,'Claude Usage Daily'!$A$5:$A$233,"<="&C15)) | O15: =IF(J15="","",IF(N15="",J15*'Overall'!$G$29/DeliveryDays,N15)+J15*('Overall'!$D$43+'Overall'!$D$44+'Overall'!$D$45)/DeliveryDays+N(M15)) | P15: =IF(O15="","",O15-N(I15))
A16: 12 | B16: =IF(OR(D16="",ProjectStart=""),"",WORKDAY(ProjectStart,(12-1)*SprintDays)) | C16: =IF(B16="","",WORKDAY(B16,SprintDays-1)) | D16: =IF(OR(MIN(SprintDays,MAX(0,DeliveryDays-(12-1)*SprintDays))>0,AND(ProjectStart<>"",LastActual<>"",WORKDAY(ProjectStart,(12-1)*SprintDays)<=N(LastActual))),MIN(SprintDays,MAX(0,DeliveryDays-(12-1)*SprintDays)),"") | F16: =IF(D16="","",D16*'Overall'!$G$29/DeliveryDays) | G16: =IF(D16="","",D16*('Overall'!$D$43+'Overall'!$D$44+'Overall'!$D$45)/DeliveryDays) | I16: =IF(D16="","",F16+G16+N(H16)) | J16: =IF(OR(B16="",LastActual="",B16>N(LastActual)),"",NETWORKDAYS(B16,MIN(C16,LastActual))) | K16: =IF(J16="","",COUNTIFS('Project Timeline'!$A$5:$A$20,"story",'Project Timeline'!$F$5:$F$20,">="&B16,'Project Timeline'!$F$5:$F$20,"<="&C16)) | M16: =IF(J16="","",SUMIFS('Claude Usage Daily'!$O$5:$O$233,'Claude Usage Daily'!$A$5:$A$233,">="&B16,'Claude Usage Daily'!$A$5:$A$233,"<="&C16)) | O16: =IF(J16="","",IF(N16="",J16*'Overall'!$G$29/DeliveryDays,N16)+J16*('Overall'!$D$43+'Overall'!$D$44+'Overall'!$D$45)/DeliveryDays+N(M16)) | P16: =IF(O16="","",O16-N(I16))
A17: Total | D17: =SUM(D5:D16) | F17: =SUM(F5:F16) | G17: =SUM(G5:G16) | H17: =SUM(H5:H16) | I17: =SUM(I5:I16) | J17: =SUM(J5:J16) | K17: =SUM(K5:K16) | M17: =SUM(M5:M16) | N17: =SUM(N5:N16) | O17: =SUM(O5:O16) | P17: =SUM(P5:P16)

Sheet Phase Budgets
A1: Phase budgets: Claude API budget and actual per planning phase
A2: In USD, at Claude API list prices. The budget each planning phase may spend (test design, governance, diagrams, course corrections ...), set once the epics and sprint plan are done; the epics and sprints carry their own budgets on their sheets. Actual: the phase's Claude cost from the ledger (Claude Usage Detail) once the close-out sheets are in. A control figure: not added to any total. Blue cells are inputs; name a phase as the token ledger does.
A4: Phase | B4: Claude API budget (USD) | C4: Claude API actual (USD) | D4: Variance (USD) | E4: Variance % | F4: Cited from
A5: governance (Jules) | B5: 40 | C5: =IF(A5="","",SUMIFS('Claude Usage Detail'!$P$5:$P$19,'Claude Usage Detail'!$B$5:$B$19,A5)) | D5: =IF(OR(A5="",C5=""),"",C5-N(B5)) | E5: =IF(OR(D5="",N(B5)=0),"",C5/B5-1) | F5: owner: Delivery Manager (synthetic), 2026-09-28
A6: architecture docs (Da Vinci) | B6: 25 | C6: =IF(A6="","",SUMIFS('Claude Usage Detail'!$P$5:$P$19,'Claude Usage Detail'!$B$5:$B$19,A6)) | D6: =IF(OR(A6="",C6=""),"",C6-N(B6)) | E6: =IF(OR(D6="",N(B6)=0),"",C6/B6-1) | F6: owner: Delivery Manager (synthetic), 2026-09-28
A7: test design | B7: 30 | C7: =IF(A7="","",SUMIFS('Claude Usage Detail'!$P$5:$P$19,'Claude Usage Detail'!$B$5:$B$19,A7)) | D7: =IF(OR(A7="",C7=""),"",C7-N(B7)) | E7: =IF(OR(D7="",N(B7)=0),"",C7/B7-1) | F7: owner: Delivery Manager (synthetic), 2026-09-28
C8: =IF(A8="","",SUMIFS('Claude Usage Detail'!$P$5:$P$19,'Claude Usage Detail'!$B$5:$B$19,A8)) | D8: =IF(OR(A8="",C8=""),"",C8-N(B8)) | E8: =IF(OR(D8="",N(B8)=0),"",C8/B8-1)
C9: =IF(A9="","",SUMIFS('Claude Usage Detail'!$P$5:$P$19,'Claude Usage Detail'!$B$5:$B$19,A9)) | D9: =IF(OR(A9="",C9=""),"",C9-N(B9)) | E9: =IF(OR(D9="",N(B9)=0),"",C9/B9-1)
C10: =IF(A10="","",SUMIFS('Claude Usage Detail'!$P$5:$P$19,'Claude Usage Detail'!$B$5:$B$19,A10)) | D10: =IF(OR(A10="",C10=""),"",C10-N(B10)) | E10: =IF(OR(D10="",N(B10)=0),"",C10/B10-1)
A11: Total | B11: =SUM(B5:B10) | C11: =SUM(C5:C10) | D11: =SUM(D5:D10)

Sheet Revenue
A1: Revenue
A2: Revenue the solution earns, per year after go-live, in USD, from the owner or the business case; each stream cites its source. Years past the horizon are ignored. Blue cells are inputs.
A4: # | B4: Stream | C4: Basis | D4: Year 1 | E4: Year 2 | F4: Year 3 | G4: Year 4 | H4: Year 5 | I4: Cited from | J4: Note
A5: 1 | B5: Application processing fees | C5: $10 per application; 30,000 in year 1, +25% a year | D5: 300000 | E5: 375000 | F5: 468750 | G5: 585938 | H5: 732422 | I5: _bmad-output/specs/SPEC.md 7 Business case
A9: Total | D9: =SUM(D5:D8) | E9: =SUM(E5:E8) | F9: =SUM(F5:F8) | G9: =SUM(G5:G8) | H9: =SUM(H5:H8)

Sheet Rate Card
A1: Employee rate card
A2: Day rates in USD. Source: Synthetic sample rates, not a real rate card; updated 2026-09-28. Blue cells are inputs; the team and support tables look roles up here.
A4: Role | B4: Day rate (USD) | C4: Note
A5: Project Manager | B5: 760
A6: Solution Architect | B6: 950
A7: Tech Lead | B7: 870
A8: Developer | B8: 650
A9: QA Engineer | B9: 545
A10: DevOps Engineer | B10: 710

Sheet Other Costs
A1: Other one-off costs
A2: Licences, tests, training and other one-off costs of the build, outside the environments and the team, in USD.
A4: # | B4: Item | C4: Amount (USD) | D4: Cited from | E4: Note | F4: Epic
A5: 1 | B5: Penetration test | C5: 12000 | D5: owner: Security Lead, 2026-09-28 | F5: 2
A6: 2 | B6: GitHub Enterprise seats (12 months) | C6: 8700 | D6: assumption: 7 seats at list price
A10: Total | C10: =SUM(C5:C9)

Sheet Run Costs
A1: Recurring run costs (OPEX)
A2: Yearly costs of running the solution outside the cloud environments and the support team: support contracts, licences, subscriptions. In USD per year; the Multi-Year sheet escalates them by the yearly increase.
A4: # | B4: Item | C4: Annual cost (USD) | D4: Cited from | E4: Note
A5: 1 | B5: Azure support plan (Standard) | C5: 1200 | D5: assumption: Standard support at list price
A6: 2 | B6: GitHub Enterprise seats (4 for support) | C6: 1000 | D6: assumption: 4 seats at list price
A10: Total | C10: =SUM(C5:C9)

Sheet Dev
A1: Dev environment
A2: Azure retail list prices (pay-as-you-go) in uaenorth, USD, fetched 2026-09-28. Daily cost is the monthly cost spread over the year (x 12 / 365). Blue cells are inputs.
A4: # | B4: Component | C4: Azure service | D4: SKU / tier | E4: Unit | F4: Unit price (USD) | G4: Quantity | H4: Usage per month | I4: Monthly cost (USD) | J4: Daily cost (USD) | K4: Annual cost (USD) | L4: Cited from | M4: Price source | N4: Note | O4: Environment
A5: 1 | B5: AKS nodes | C5: Virtual Machines | D5: Standard_D4s_v5 | E5: 1 Hour | F5: 0.235 | G5: 2 | H5: 220 | I5: =F5*G5*H5*FxRate | J5: =I5*12/365 | K5: =I5*12 | L5: _bmad-output/planning-artifacts/architecture/falcon/ARCHITECTURE-SPINE.md AD-1 | M5: Azure Retail Prices API, Virtual Machines Dsv5 Series / D4s v5, uaenorth, USD per 1 Hour, meterId 75a8da05-74dd-5b32-bb86-4f5cc74cdb60, fetched 2026-09-28 | N5: Dev nodes stopped outside working hours | O5: Dev
A6: 2 | B6: Customer database | C6: SQL Database | D6: General Purpose Gen5, 2 vCore | E6: 1 vCore Hour | F6: 0.253 | G6: 2 | H6: =HoursPerMonth | I6: =F6*G6*H6*FxRate | J6: =I6*12/365 | K6: =I6*12 | L6: _bmad-output/planning-artifacts/architecture/falcon/ARCHITECTURE-SPINE.md AD-2 | M6: Synthetic sample price (not looked up) | O6: Dev
A7: 3 | B7: Document storage | C7: Storage | D7: Blob Hot LRS | E7: 1 GB/Month | F7: 0.019 | G7: 50 | H7: 1 | I7: =F7*G7*H7*FxRate | J7: =I7*12/365 | K7: =I7*12 | L7: assumption: 50 GB of test documents | M7: Synthetic sample price (not looked up) | O7: Dev
A8: 4 | B8: Secrets | C8: Key Vault | D8: Standard | E8: 10K operations | F8: 0.03 | G8: 30 | H8: 1 | I8: =F8*G8*H8*FxRate | J8: =I8*12/365 | K8: =I8*12 | L8: _bmad-output/planning-artifacts/architecture/falcon/ARCHITECTURE-SPINE.md AD-5 | M8: Synthetic sample price (not looked up) | O8: Dev
A9: 5 | B9: Logs and metrics | C9: Log Analytics | D9: Pay-as-you-go | E9: 1 GB | F9: 2.76 | G9: 5 | H9: 1 | I9: =F9*G9*H9*FxRate | J9: =I9*12/365 | K9: =I9*12 | L9: _bmad-output/planning-artifacts/architecture/falcon/ARCHITECTURE-SPINE.md AD-5 | M9: Synthetic sample price (not looked up) | O9: Dev
I10: =IF(F10="","",F10*G10*H10*FxRate) | J10: =IF(I10="","",I10*12/365) | K10: =IF(I10="","",I10*12) | O10: Dev
I11: =IF(F11="","",F11*G11*H11*FxRate) | J11: =IF(I11="","",I11*12/365) | K11: =IF(I11="","",I11*12) | O11: Dev
I12: =IF(F12="","",F12*G12*H12*FxRate) | J12: =IF(I12="","",I12*12/365) | K12: =IF(I12="","",I12*12) | O12: Dev
A13: Total | I13: =SUM(I5:I12) | J13: =SUM(J5:J12) | K13: =SUM(K5:K12)

Sheet Test
A1: Test environment
A2: Azure retail list prices (pay-as-you-go) in uaenorth, USD, fetched 2026-09-28. Daily cost is the monthly cost spread over the year (x 12 / 365). Blue cells are inputs.
A4: # | B4: Component | C4: Azure service | D4: SKU / tier | E4: Unit | F4: Unit price (USD) | G4: Quantity | H4: Usage per month | I4: Monthly cost (USD) | J4: Daily cost (USD) | K4: Annual cost (USD) | L4: Cited from | M4: Price source | N4: Note | O4: Environment
A5: 1 | B5: AKS nodes | C5: Virtual Machines | D5: Standard_D4s_v5 | E5: 1 Hour | F5: 0.235 | G5: 2 | H5: =HoursPerMonth | I5: =F5*G5*H5*FxRate | J5: =I5*12/365 | K5: =I5*12 | L5: _bmad-output/planning-artifacts/architecture/falcon/ARCHITECTURE-SPINE.md AD-1 | M5: Azure Retail Prices API, Virtual Machines Dsv5 Series / D4s v5, uaenorth, USD per 1 Hour, meterId 75a8da05-74dd-5b32-bb86-4f5cc74cdb60, fetched 2026-09-28 | O5: Test
A6: 2 | B6: Customer database | C6: SQL Database | D6: General Purpose Gen5, 2 vCore | E6: 1 vCore Hour | F6: 0.253 | G6: 2 | H6: =HoursPerMonth | I6: =F6*G6*H6*FxRate | J6: =I6*12/365 | K6: =I6*12 | L6: _bmad-output/planning-artifacts/architecture/falcon/ARCHITECTURE-SPINE.md AD-2 | M6: Synthetic sample price (not looked up) | O6: Test
A7: 3 | B7: Document storage | C7: Storage | D7: Blob Hot LRS | E7: 1 GB/Month | F7: 0.019 | G7: 50 | H7: 1 | I7: =F7*G7*H7*FxRate | J7: =I7*12/365 | K7: =I7*12 | L7: assumption: 50 GB of test documents | M7: Synthetic sample price (not looked up) | O7: Test
A8: 4 | B8: Secrets | C8: Key Vault | D8: Standard | E8: 10K operations | F8: 0.03 | G8: 30 | H8: 1 | I8: =F8*G8*H8*FxRate | J8: =I8*12/365 | K8: =I8*12 | L8: _bmad-output/planning-artifacts/architecture/falcon/ARCHITECTURE-SPINE.md AD-5 | M8: Synthetic sample price (not looked up) | O8: Test
A9: 5 | B9: Logs and metrics | C9: Log Analytics | D9: Pay-as-you-go | E9: 1 GB | F9: 2.76 | G9: 5 | H9: 1 | I9: =F9*G9*H9*FxRate | J9: =I9*12/365 | K9: =I9*12 | L9: _bmad-output/planning-artifacts/architecture/falcon/ARCHITECTURE-SPINE.md AD-5 | M9: Synthetic sample price (not looked up) | O9: Test
A10: 6 | B10: Edge | C10: Azure Front Door Service | D10: Standard base fee | E10: 1 Month | F10: 35 | G10: 1 | H10: 1 | I10: =F10*G10*H10*FxRate | J10: =I10*12/365 | K10: =I10*12 | L10: _bmad-output/planning-artifacts/architecture/falcon/ARCHITECTURE-SPINE.md AD-4 | M10: Synthetic sample price (not looked up) | O10: Test
I11: =IF(F11="","",F11*G11*H11*FxRate) | J11: =IF(I11="","",I11*12/365) | K11: =IF(I11="","",I11*12) | O11: Test
I12: =IF(F12="","",F12*G12*H12*FxRate) | J12: =IF(I12="","",I12*12/365) | K12: =IF(I12="","",I12*12) | O12: Test
I13: =IF(F13="","",F13*G13*H13*FxRate) | J13: =IF(I13="","",I13*12/365) | K13: =IF(I13="","",I13*12) | O13: Test
A14: Total | I14: =SUM(I5:I13) | J14: =SUM(J5:J13) | K14: =SUM(K5:K13)

Sheet Prod
A1: Prod environment
A2: Azure retail list prices (pay-as-you-go) in uaenorth, USD, fetched 2026-09-28. Daily cost is the monthly cost spread over the year (x 12 / 365). Blue cells are inputs.
A4: # | B4: Component | C4: Azure service | D4: SKU / tier | E4: Unit | F4: Unit price (USD) | G4: Quantity | H4: Usage per month | I4: Monthly cost (USD) | J4: Daily cost (USD) | K4: Annual cost (USD) | L4: Cited from | M4: Price source | N4: Note | O4: Environment
A5: 1 | B5: AKS nodes | C5: Virtual Machines | D5: Standard_D4s_v5 | E5: 1 Hour | F5: 0.235 | G5: 3 | H5: =HoursPerMonth | I5: =F5*G5*H5*FxRate | J5: =I5*12/365 | K5: =I5*12 | L5: _bmad-output/planning-artifacts/architecture/falcon/ARCHITECTURE-SPINE.md AD-1 | M5: Azure Retail Prices API, Virtual Machines Dsv5 Series / D4s v5, uaenorth, USD per 1 Hour, meterId 75a8da05-74dd-5b32-bb86-4f5cc74cdb60, fetched 2026-09-28 | O5: Prod
A6: 2 | B6: Customer database | C6: SQL Database | D6: General Purpose Gen5, 4 vCore | E6: 1 vCore Hour | F6: 0.253 | G6: 4 | H6: =HoursPerMonth | I6: =F6*G6*H6*FxRate | J6: =I6*12/365 | K6: =I6*12 | L6: _bmad-output/planning-artifacts/architecture/falcon/ARCHITECTURE-SPINE.md AD-2 | M6: Synthetic sample price (not looked up) | O6: Prod
A7: 3 | B7: Document storage | C7: Storage | D7: Blob Hot LRS | E7: 1 GB/Month | F7: 0.019 | G7: 500 | H7: 1 | I7: =F7*G7*H7*FxRate | J7: =I7*12/365 | K7: =I7*12 | L7: _bmad-output/planning-artifacts/architecture/falcon/ARCHITECTURE-SPINE.md AD-3 | M7: Synthetic sample price (not looked up) | O7: Prod
A8: 4 | B8: Secrets | C8: Key Vault | D8: Standard | E8: 10K operations | F8: 0.03 | G8: 30 | H8: 1 | I8: =F8*G8*H8*FxRate | J8: =I8*12/365 | K8: =I8*12 | L8: _bmad-output/planning-artifacts/architecture/falcon/ARCHITECTURE-SPINE.md AD-5 | M8: Synthetic sample price (not looked up) | O8: Prod
A9: 5 | B9: Logs and metrics | C9: Log Analytics | D9: Pay-as-you-go | E9: 1 GB | F9: 2.76 | G9: 30 | H9: 1 | I9: =F9*G9*H9*FxRate | J9: =I9*12/365 | K9: =I9*12 | L9: _bmad-output/planning-artifacts/architecture/falcon/ARCHITECTURE-SPINE.md AD-5 | M9: Synthetic sample price (not looked up) | O9: Prod
A10: 6 | B10: Edge | C10: Azure Front Door Service | D10: Standard base fee | E10: 1 Month | F10: 35 | G10: 1 | H10: 1 | I10: =F10*G10*H10*FxRate | J10: =I10*12/365 | K10: =I10*12 | L10: _bmad-output/planning-artifacts/architecture/falcon/ARCHITECTURE-SPINE.md AD-4 | M10: Synthetic sample price (not looked up) | O10: Prod
I11: =IF(F11="","",F11*G11*H11*FxRate) | J11: =IF(I11="","",I11*12/365) | K11: =IF(I11="","",I11*12) | O11: Prod
I12: =IF(F12="","",F12*G12*H12*FxRate) | J12: =IF(I12="","",I12*12/365) | K12: =IF(I12="","",I12*12) | O12: Prod
I13: =IF(F13="","",F13*G13*H13*FxRate) | J13: =IF(I13="","",I13*12/365) | K13: =IF(I13="","",I13*12) | O13: Prod
A14: Total | I14: =SUM(I5:I13) | J14: =SUM(J5:J13) | K14: =SUM(K5:K13)

Sheet Claude Prices
A1: Claude API list prices
A2: USD per million tokens, from https://platform.claude.com/docs/en/about-claude/pricing, read 2026-09-28. Blue cells are inputs.
A4: Pricing model | B4: Name | C4: Input | D4: Cache write 5m | E4: Cache write 1h | F4: Cache read | G4: Output
A5: claude-fable-5 | B5: Claude Fable 5 | C5: 10 | D5: 12.5 | E5: 20 | F5: 1 | G5: 50
A6: claude-fable-5-1 | B6: Claude Fable 5.1 | C6: 10 | D6: 12.5 | E6: 20 | F6: 0.25 | G6: 50
A7: claude-haiku-3-5 | B7: Claude Haiku 3.5 | C7: 0.8 | D7: 1 | E7: 1.6 | F7: 0.08 | G7: 4
A8: claude-haiku-4-5 | B8: Claude Haiku 4.5 | C8: 1 | D8: 1.25 | E8: 2 | F8: 0.1 | G8: 5
A9: claude-mythos-5 | B9: Claude Mythos 5 | C9: 10 | D9: 12.5 | E9: 20 | F9: 1 | G9: 50
A10: claude-mythos-5-1 | B10: Claude Mythos 5.1 | C10: 10 | D10: 12.5 | E10: 20 | F10: 0.25 | G10: 50
A11: claude-opus-4 | B11: Claude Opus 4 | C11: 15 | D11: 18.75 | E11: 30 | F11: 1.5 | G11: 75
A12: claude-opus-4-1 | B12: Claude Opus 4.1 | C12: 15 | D12: 18.75 | E12: 30 | F12: 1.5 | G12: 75
A13: claude-opus-4-5 | B13: Claude Opus 4.5 | C13: 5 | D13: 6.25 | E13: 10 | F13: 0.5 | G13: 25
A14: claude-opus-4-6 | B14: Claude Opus 4.6 | C14: 5 | D14: 6.25 | E14: 10 | F14: 0.5 | G14: 25
A15: claude-opus-4-7 | B15: Claude Opus 4.7 | C15: 5 | D15: 6.25 | E15: 10 | F15: 0.5 | G15: 25
A16: claude-opus-4-8 | B16: Claude Opus 4.8 | C16: 5 | D16: 6.25 | E16: 10 | F16: 0.5 | G16: 25
... A22: claude-sonnet-5 | B22: Claude Sonnet 5 | C22: 2 | D22: 2.5 | E22: 4 | F22: 0.2 | G22: 10

Sheet Claude Usage
A1: Claude API usage
A2: API calls and tokens counted from this project's Claude Code logs, costed at Claude API list prices. On a Pro, Max, Team or Enterprise subscription the bill is per seat: this is the API-equivalent cost.
A4: Model | B4: Calls | C4: Input tokens | D4: Cache write 5m tokens | E4: Cache write 1h tokens | F4: Cache read tokens | G4: Output tokens | H4: Cost (USD) | I4: Cost (USD)
A5: claude-haiku-4-5-20251001 | B5: =SUMIFS('Claude Usage Detail'!$I$5:$I$19,'Claude Usage Detail'!$E$5:$E$19,"="&$A5) | C5: =SUMIFS('Claude Usage Detail'!$J$5:$J$19,'Claude Usage Detail'!$E$5:$E$19,"="&$A5) | D5: =SUMIFS('Claude Usage Detail'!$K$5:$K$19,'Claude Usage Detail'!$E$5:$E$19,"="&$A5) | E5: =SUMIFS('Claude Usage Detail'!$L$5:$L$19,'Claude Usage Detail'!$E$5:$E$19,"="&$A5) | F5: =SUMIFS('Claude Usage Detail'!$M$5:$M$19,'Claude Usage Detail'!$E$5:$E$19,"="&$A5) | G5: =SUMIFS('Claude Usage Detail'!$N$5:$N$19,'Claude Usage Detail'!$E$5:$E$19,"="&$A5) | H5: =SUMIFS('Claude Usage Detail'!$O$5:$O$19,'Claude Usage Detail'!$E$5:$E$19,"="&$A5) | I5: =SUMIFS('Claude Usage Detail'!$P$5:$P$19,'Claude Usage Detail'!$E$5:$E$19,"="&$A5)
A6: claude-opus-5-5 | B6: =SUMIFS('Claude Usage Detail'!$I$5:$I$19,'Claude Usage Detail'!$E$5:$E$19,"="&$A6) | C6: =SUMIFS('Claude Usage Detail'!$J$5:$J$19,'Claude Usage Detail'!$E$5:$E$19,"="&$A6) | D6: =SUMIFS('Claude Usage Detail'!$K$5:$K$19,'Claude Usage Detail'!$E$5:$E$19,"="&$A6) | E6: =SUMIFS('Claude Usage Detail'!$L$5:$L$19,'Claude Usage Detail'!$E$5:$E$19,"="&$A6) | F6: =SUMIFS('Claude Usage Detail'!$M$5:$M$19,'Claude Usage Detail'!$E$5:$E$19,"="&$A6) | G6: =SUMIFS('Claude Usage Detail'!$N$5:$N$19,'Claude Usage Detail'!$E$5:$E$19,"="&$A6) | H6: =SUMIFS('Claude Usage Detail'!$O$5:$O$19,'Claude Usage Detail'!$E$5:$E$19,"="&$A6) | I6: =SUMIFS('Claude Usage Detail'!$P$5:$P$19,'Claude Usage Detail'!$E$5:$E$19,"="&$A6)
A7: claude-sonnet-5 | B7: =SUMIFS('Claude Usage Detail'!$I$5:$I$19,'Claude Usage Detail'!$E$5:$E$19,"="&$A7) | C7: =SUMIFS('Claude Usage Detail'!$J$5:$J$19,'Claude Usage Detail'!$E$5:$E$19,"="&$A7) | D7: =SUMIFS('Claude Usage Detail'!$K$5:$K$19,'Claude Usage Detail'!$E$5:$E$19,"="&$A7) | E7: =SUMIFS('Claude Usage Detail'!$L$5:$L$19,'Claude Usage Detail'!$E$5:$E$19,"="&$A7) | F7: =SUMIFS('Claude Usage Detail'!$M$5:$M$19,'Claude Usage Detail'!$E$5:$E$19,"="&$A7) | G7: =SUMIFS('Claude Usage Detail'!$N$5:$N$19,'Claude Usage Detail'!$E$5:$E$19,"="&$A7) | H7: =SUMIFS('Claude Usage Detail'!$O$5:$O$19,'Claude Usage Detail'!$E$5:$E$19,"="&$A7) | I7: =SUMIFS('Claude Usage Detail'!$P$5:$P$19,'Claude Usage Detail'!$E$5:$E$19,"="&$A7)
A8: Total | B8: =SUM(B5:B7) | C8: =SUM(C5:C7) | D8: =SUM(D5:D7) | E8: =SUM(E5:E7) | F8: =SUM(F5:F7) | G8: =SUM(G5:G7) | H8: =SUM(H5:H7) | I8: =SUM(I5:I7)

Sheet Claude Usage Detail
A1: Claude API calls by work item and model
A2: From the token ledger (claude_usage.csv). Cost = tokens x the Claude Prices sheet; models with no price cost 0.
A4: Kind | B4: Work item | C4: Story no | D4: Title | E4: Model | F4: Pricing model | G4: First call | H4: Last call | I4: Calls | J4: Input tokens | K4: Cache write 5m tokens | L4: Cache write 1h tokens | M4: Cache read tokens | N4: Output tokens | O4: Cost (USD) | P4: Cost (USD)
A5: planning | B5: brainstorming | E5: claude-opus-5-5 | F5: claude-opus-5-5 | G5: 46027.375 | H5: 46027.708 | I5: 42 | J5: 9000 | K5: 120000 | L5: 380000 | M5: 6100000 | N5: 95000 | O5: =IFERROR((J5*VLOOKUP($F5,'Claude Prices'!$A$5:$G$22,3,FALSE)+K5*VLOOKUP($F5,'Claude Prices'!$A$5:$G$22,4,FALSE)+L5*VLOOKUP($F5,'Claude Prices'!$A$5:$G$22,5,FALSE)+M5*VLOOKUP($F5,'Claude Prices'!$A$5:$G$22,6,FALSE)+N5*VLOOKUP($F5,'Claude Prices'!$A$5:$G$22,7,FALSE))/1000000,0) | P5: =O5*ClaudeFxRate
A6: planning | B6: spec | E6: claude-opus-5-5 | F6: claude-opus-5-5 | G6: 46028.375 | H6: 46030.708 | I6: 118 | J6: 21000 | K6: 300000 | L6: 1250000 | M6: 21400000 | N6: 310000 | O6: =IFERROR((J6*VLOOKUP($F6,'Claude Prices'!$A$5:$G$22,3,FALSE)+K6*VLOOKUP($F6,'Claude Prices'!$A$5:$G$22,4,FALSE)+L6*VLOOKUP($F6,'Claude Prices'!$A$5:$G$22,5,FALSE)+M6*VLOOKUP($F6,'Claude Prices'!$A$5:$G$22,6,FALSE)+N6*VLOOKUP($F6,'Claude Prices'!$A$5:$G$22,7,FALSE))/1000000,0) | P6: =O6*ClaudeFxRate
A7: planning | B7: architecture | E7: claude-opus-5-5 | F7: claude-opus-5-5 | G7: 46034.375 | H7: 46044.708 | I7: 356 | J7: 64000 | K7: 820000 | L7: 3900000 | M7: 68200000 | N7: 905000 | O7: =IFERROR((J7*VLOOKUP($F7,'Claude Prices'!$A$5:$G$22,3,FALSE)+K7*VLOOKUP($F7,'Claude Prices'!$A$5:$G$22,4,FALSE)+L7*VLOOKUP($F7,'Claude Prices'!$A$5:$G$22,5,FALSE)+M7*VLOOKUP($F7,'Claude Prices'!$A$5:$G$22,6,FALSE)+N7*VLOOKUP($F7,'Claude Prices'!$A$5:$G$22,7,FALSE))/1000000,0) | P7: =O7*ClaudeFxRate
A8: planning | B8: UX design | E8: claude-sonnet-5 | F8: claude-sonnet-5 | G8: 46041.375 | H8: 46045.708 | I8: 164 | J8: 30000 | K8: 410000 | L8: 1500000 | M8: 24800000 | N8: 420000 | O8: =IFERROR((J8*VLOOKUP($F8,'Claude Prices'!$A$5:$G$22,3,FALSE)+K8*VLOOKUP($F8,'Claude Prices'!$A$5:$G$22,4,FALSE)+L8*VLOOKUP($F8,'Claude Prices'!$A$5:$G$22,5,FALSE)+M8*VLOOKUP($F8,'Claude Prices'!$A$5:$G$22,6,FALSE)+N8*VLOOKUP($F8,'Claude Prices'!$A$5:$G$22,7,FALSE))/1000000,0) | P8: =O8*ClaudeFxRate
A9: planning | B9: epics & stories | E9: claude-sonnet-5 | F9: claude-sonnet-5 | G9: 46048.375 | H9: 46049.708 | I9: 97 | J9: 18000 | K9: 260000 | L9: 900000 | M9: 14600000 | N9: 260000 | O9: =IFERROR((J9*VLOOKUP($F9,'Claude Prices'!$A$5:$G$22,3,FALSE)+K9*VLOOKUP($F9,'Claude Prices'!$A$5:$G$22,4,FALSE)+L9*VLOOKUP($F9,'Claude Prices'!$A$5:$G$22,5,FALSE)+M9*VLOOKUP($F9,'Claude Prices'!$A$5:$G$22,6,FALSE)+N9*VLOOKUP($F9,'Claude Prices'!$A$5:$G$22,7,FALSE))/1000000,0) | P9: =O9*ClaudeFxRate
A10: planning | B10: governance (Jules) | E10: claude-opus-5-5 | F10: claude-opus-5-5 | G10: 46042.375 | H10: 46073.708 | I10: 88 | J10: 15000 | K10: 210000 | L10: 760000 | M10: 12500000 | N10: 180000 | O10: =IFERROR((J10*VLOOKUP($F10,'Claude Prices'!$A$5:$G$22,3,FALSE)+K10*VLOOKUP($F10,'Claude Prices'!$A$5:$G$22,4,FALSE)+L10*VLOOKUP($F10,'Claude Prices'!$A$5:$G$22,5,FALSE)+M10*VLOOKUP($F10,'Claude Prices'!$A$5:$G$22,6,FALSE)+N10*VLOOKUP($F10,'Claude Prices'!$A$5:$G$22,7,FALSE))/1000000,0) | P10: =O10*ClaudeFxRate
A11: planning | B11: architecture docs (Da Vinci) | E11: claude-opus-5-5 | F11: claude-opus-5-5 | G11: 46042.375 | H11: 46044.708 | I11: 61 | J11: 11000 | K11: 150000 | L11: 520000 | M11: 8700000 | N11: 140000 | O11: =IFERROR((J11*VLOOKUP($F11,'Claude Prices'!$A$5:$G$22,3,FALSE)+K11*VLOOKUP($F11,'Claude Prices'!$A$5:$G$22,4,FALSE)+L11*VLOOKUP($F11,'Claude Prices'!$A$5:$G$22,5,FALSE)+M11*VLOOKUP($F11,'Claude Prices'!$A$5:$G$22,6,FALSE)+N11*VLOOKUP($F11,'Claude Prices'!$A$5:$G$22,7,FALSE))/1000000,0) | P11: =O11*ClaudeFxRate
A12: story | B12: FAL-11 | C12: 1.1 | D12: Sign in with Entra ID | E12: claude-sonnet-5 | F12: claude-sonnet-5 | G12: 46083.375 | H12: 46098.708 | I12: 212 | J12: 40000 | K12: 500000 | L12: 2100000 | M12: 33900000 | N12: 520000 | O12: =IFERROR((J12*VLOOKUP($F12,'Claude Prices'!$A$5:$G$22,3,FALSE)+K12*VLOOKUP($F12,'Claude Prices'!$A$5:$G$22,4,FALSE)+L12*VLOOKUP($F12,'Claude Prices'!$A$5:$G$22,5,FALSE)+M12*VLOOKUP($F12,'Claude Prices'!$A$5:$G$22,6,FALSE)+N12*VLOOKUP($F12,'Claude Prices'!$A$5:$G$22,7,FALSE))/1000000,0) | P12: =O12*ClaudeFxRate
A13: story | B13: FAL-12 | C13: 1.2 | D13: Start an application | E13: claude-sonnet-5 | F13: claude-sonnet-5 | G13: 46099.375 | H13: 46114.708 | I13: 305 | J13: 57000 | K13: 720000 | L13: 3000000 | M13: 48700000 | N13: 760000 | O13: =IFERROR((J13*VLOOKUP($F13,'Claude Prices'!$A$5:$G$22,3,FALSE)+K13*VLOOKUP($F13,'Claude Prices'!$A$5:$G$22,4,FALSE)+L13*VLOOKUP($F13,'Claude Prices'!$A$5:$G$22,5,FALSE)+M13*VLOOKUP($F13,'Claude Prices'!$A$5:$G$22,6,FALSE)+N13*VLOOKUP($F13,'Claude Prices'!$A$5:$G$22,7,FALSE))/1000000,0) | P13: =O13*ClaudeFxRate
A14: story | B14: FAL-13 | C14: 1.3 | D14: Upload documents | E14: claude-sonnet-5 | F14: claude-sonnet-5 | G14: 46115.375 | H14: 46132.708 | I14: 248 | J14: 46000 | K14: 600000 | L14: 2500000 | M14: 40100000 | N14: 610000 | O14: =IFERROR((J14*VLOOKUP($F14,'Claude Prices'!$A$5:$G$22,3,FALSE)+K14*VLOOKUP($F14,'Claude Prices'!$A$5:$G$22,4,FALSE)+L14*VLOOKUP($F14,'Claude Prices'!$A$5:$G$22,5,FALSE)+M14*VLOOKUP($F14,'Claude Prices'!$A$5:$G$22,6,FALSE)+N14*VLOOKUP($F14,'Claude Prices'!$A$5:$G$22,7,FALSE))/1000000,0) | P14: =O14*ClaudeFxRate
A15: story | B15: FAL-13 | C15: 1.3 | D15: Upload documents | E15: claude-haiku-4-5-20251001 | F15: claude-haiku-4-5 | G15: 46115.375 | H15: 46132.708 | I15: 96 | J15: 18000 | K15: 90000 | L15: 300000 | M15: 6200000 | N15: 70000 | O15: =IFERROR((J15*VLOOKUP($F15,'Claude Prices'!$A$5:$G$22,3,FALSE)+K15*VLOOKUP($F15,'Claude Prices'!$A$5:$G$22,4,FALSE)+L15*VLOOKUP($F15,'Claude Prices'!$A$5:$G$22,5,FALSE)+M15*VLOOKUP($F15,'Claude Prices'!$A$5:$G$22,6,FALSE)+N15*VLOOKUP($F15,'Claude Prices'!$A$5:$G$22,7,FALSE))/1000000,0) | P15: =O15*ClaudeFxRate
A16: story | B16: FAL-21 | C16: 2.1 | D16: Review queue | E16: claude-sonnet-5 | F16: claude-sonnet-5 | G16: 46133.375 | H16: 46154.708 | I16: 289 | J16: 54000 | K16: 690000 | L16: 2900000 | M16: 46300000 | N16: 710000 | O16: =IFERROR((J16*VLOOKUP($F16,'Claude Prices'!$A$5:$G$22,3,FALSE)+K16*VLOOKUP($F16,'Claude Prices'!$A$5:$G$22,4,FALSE)+L16*VLOOKUP($F16,'Claude Prices'!$A$5:$G$22,5,FALSE)+M16*VLOOKUP($F16,'Claude Prices'!$A$5:$G$22,6,FALSE)+N16*VLOOKUP($F16,'Claude Prices'!$A$5:$G$22,7,FALSE))/1000000,0) | P16: =O16*ClaudeFxRate
A17: story | B17: FAL-22 | C17: 2.2 | D17: Approve or reject | E17: claude-sonnet-5 | F17: claude-sonnet-5 | G17: 46155.375 | H17: 46176.708 | I17: 231 | J17: 43000 | K17: 560000 | L17: 2300000 | M17: 37000000 | N17: 570000 | O17: =IFERROR((J17*VLOOKUP($F17,'Claude Prices'!$A$5:$G$22,3,FALSE)+K17*VLOOKUP($F17,'Claude Prices'!$A$5:$G$22,4,FALSE)+L17*VLOOKUP($F17,'Claude Prices'!$A$5:$G$22,5,FALSE)+M17*VLOOKUP($F17,'Claude Prices'!$A$5:$G$22,6,FALSE)+N17*VLOOKUP($F17,'Claude Prices'!$A$5:$G$22,7,FALSE))/1000000,0) | P17: =O17*ClaudeFxRate
A18: story | B18: FAL-23 | C18: 2.3 | D18: Notify the customer | E18: claude-sonnet-5 | F18: claude-sonnet-5 | G18: 46177.375 | H18: 46199.708 | I18: 174 | J18: 32000 | K18: 420000 | L18: 1700000 | M18: 27800000 | N18: 430000 | O18: =IFERROR((J18*VLOOKUP($F18,'Claude Prices'!$A$5:$G$22,3,FALSE)+K18*VLOOKUP($F18,'Claude Prices'!$A$5:$G$22,4,FALSE)+L18*VLOOKUP($F18,'Claude Prices'!$A$5:$G$22,5,FALSE)+M18*VLOOKUP($F18,'Claude Prices'!$A$5:$G$22,6,FALSE)+N18*VLOOKUP($F18,'Claude Prices'!$A$5:$G$22,7,FALSE))/1000000,0) | P18: =O18*ClaudeFxRate
A19: ops | B19: merges, promotions & deploys | E19: claude-haiku-4-5-20251001 | F19: claude-haiku-4-5 | G19: 46083.375 | H19: 46199.708 | I19: 133 | J19: 25000 | K19: 110000 | L19: 420000 | M19: 8600000 | N19: 95000 | O19: =IFERROR((J19*VLOOKUP($F19,'Claude Prices'!$A$5:$G$22,3,FALSE)+K19*VLOOKUP($F19,'Claude Prices'!$A$5:$G$22,4,FALSE)+L19*VLOOKUP($F19,'Claude Prices'!$A$5:$G$22,5,FALSE)+M19*VLOOKUP($F19,'Claude Prices'!$A$5:$G$22,6,FALSE)+N19*VLOOKUP($F19,'Claude Prices'!$A$5:$G$22,7,FALSE))/1000000,0) | P19: =O19*ClaudeFxRate

Sheet Claude Usage Daily
A1: Claude API usage by day
A2: From the token ledger (claude_usage_daily.csv, refreshed after every turn). Cost = tokens x the Claude Prices sheet; models with no price cost 0.
A4: Day | B4: Kind | C4: Work item | D4: Story no | E4: Title | F4: Model | G4: Pricing model | H4: Calls | I4: Input tokens | J4: Cache write 5m tokens | K4: Cache write 1h tokens | L4: Cache read tokens | M4: Output tokens | N4: Cost (USD) | O4: Cost (USD)
A5: 46027 | B5: planning | C5: brainstorming | F5: claude-opus-5-5 | G5: claude-opus-5-5 | H5: 42 | I5: 9000 | J5: 120000 | K5: 380000 | L5: 6100000 | M5: 95000 | N5: =IFERROR((I5*VLOOKUP($G5,'Claude Prices'!$A$5:$G$22,3,FALSE)+J5*VLOOKUP($G5,'Claude Prices'!$A$5:$G$22,4,FALSE)+K5*VLOOKUP($G5,'Claude Prices'!$A$5:$G$22,5,FALSE)+L5*VLOOKUP($G5,'Claude Prices'!$A$5:$G$22,6,FALSE)+M5*VLOOKUP($G5,'Claude Prices'!$A$5:$G$22,7,FALSE))/1000000,0) | O5: =N5*ClaudeFxRate
A6: 46028 | B6: planning | C6: spec | F6: claude-opus-5-5 | G6: claude-opus-5-5 | H6: 39 | I6: 7000 | J6: 100000 | K6: 416666 | L6: 7133333 | M6: 103333 | N6: =IFERROR((I6*VLOOKUP($G6,'Claude Prices'!$A$5:$G$22,3,FALSE)+J6*VLOOKUP($G6,'Claude Prices'!$A$5:$G$22,4,FALSE)+K6*VLOOKUP($G6,'Claude Prices'!$A$5:$G$22,5,FALSE)+L6*VLOOKUP($G6,'Claude Prices'!$A$5:$G$22,6,FALSE)+M6*VLOOKUP($G6,'Claude Prices'!$A$5:$G$22,7,FALSE))/1000000,0) | O6: =N6*ClaudeFxRate
A7: 46029 | B7: planning | C7: spec | F7: claude-opus-5-5 | G7: claude-opus-5-5 | H7: 39 | I7: 7000 | J7: 100000 | K7: 416666 | L7: 7133333 | M7: 103333 | N7: =IFERROR((I7*VLOOKUP($G7,'Claude Prices'!$A$5:$G$22,3,FALSE)+J7*VLOOKUP($G7,'Claude Prices'!$A$5:$G$22,4,FALSE)+K7*VLOOKUP($G7,'Claude Prices'!$A$5:$G$22,5,FALSE)+L7*VLOOKUP($G7,'Claude Prices'!$A$5:$G$22,6,FALSE)+M7*VLOOKUP($G7,'Claude Prices'!$A$5:$G$22,7,FALSE))/1000000,0) | O7: =N7*ClaudeFxRate
A8: 46030 | B8: planning | C8: spec | F8: claude-opus-5-5 | G8: claude-opus-5-5 | H8: 40 | I8: 7000 | J8: 100000 | K8: 416668 | L8: 7133334 | M8: 103334 | N8: =IFERROR((I8*VLOOKUP($G8,'Claude Prices'!$A$5:$G$22,3,FALSE)+J8*VLOOKUP($G8,'Claude Prices'!$A$5:$G$22,4,FALSE)+K8*VLOOKUP($G8,'Claude Prices'!$A$5:$G$22,5,FALSE)+L8*VLOOKUP($G8,'Claude Prices'!$A$5:$G$22,6,FALSE)+M8*VLOOKUP($G8,'Claude Prices'!$A$5:$G$22,7,FALSE))/1000000,0) | O8: =N8*ClaudeFxRate
A9: 46034 | B9: planning | C9: architecture | F9: claude-opus-5-5 | G9: claude-opus-5-5 | H9: 39 | I9: 7111 | J9: 91111 | K9: 433333 | L9: 7577777 | M9: 100555 | N9: =IFERROR((I9*VLOOKUP($G9,'Claude Prices'!$A$5:$G$22,3,FALSE)+J9*VLOOKUP($G9,'Claude Prices'!$A$5:$G$22,4,FALSE)+K9*VLOOKUP($G9,'Claude Prices'!$A$5:$G$22,5,FALSE)+L9*VLOOKUP($G9,'Claude Prices'!$A$5:$G$22,6,FALSE)+M9*VLOOKUP($G9,'Claude Prices'!$A$5:$G$22,7,FALSE))/1000000,0) | O9: =N9*ClaudeFxRate
A10: 46035 | B10: planning | C10: architecture | F10: claude-opus-5-5 | G10: claude-opus-5-5 | H10: 39 | I10: 7111 | J10: 91111 | K10: 433333 | L10: 7577777 | M10: 100555 | N10: =IFERROR((I10*VLOOKUP($G10,'Claude Prices'!$A$5:$G$22,3,FALSE)+J10*VLOOKUP($G10,'Claude Prices'!$A$5:$G$22,4,FALSE)+K10*VLOOKUP($G10,'Claude Prices'!$A$5:$G$22,5,FALSE)+L10*VLOOKUP($G10,'Claude Prices'!$A$5:$G$22,6,FALSE)+M10*VLOOKUP($G10,'Claude Prices'!$A$5:$G$22,7,FALSE))/1000000,0) | O10: =N10*ClaudeFxRate
A11: 46036 | B11: planning | C11: architecture | F11: claude-opus-5-5 | G11: claude-opus-5-5 | H11: 39 | I11: 7111 | J11: 91111 | K11: 433333 | L11: 7577777 | M11: 100555 | N11: =IFERROR((I11*VLOOKUP($G11,'Claude Prices'!$A$5:$G$22,3,FALSE)+J11*VLOOKUP($G11,'Claude Prices'!$A$5:$G$22,4,FALSE)+K11*VLOOKUP($G11,'Claude Prices'!$A$5:$G$22,5,FALSE)+L11*VLOOKUP($G11,'Claude Prices'!$A$5:$G$22,6,FALSE)+M11*VLOOKUP($G11,'Claude Prices'!$A$5:$G$22,7,FALSE))/1000000,0) | O11: =N11*ClaudeFxRate
A12: 46037 | B12: planning | C12: architecture | F12: claude-opus-5-5 | G12: claude-opus-5-5 | H12: 39 | I12: 7111 | J12: 91111 | K12: 433333 | L12: 7577777 | M12: 100555 | N12: =IFERROR((I12*VLOOKUP($G12,'Claude Prices'!$A$5:$G$22,3,FALSE)+J12*VLOOKUP($G12,'Claude Prices'!$A$5:$G$22,4,FALSE)+K12*VLOOKUP($G12,'Claude Prices'!$A$5:$G$22,5,FALSE)+L12*VLOOKUP($G12,'Claude Prices'!$A$5:$G$22,6,FALSE)+M12*VLOOKUP($G12,'Claude Prices'!$A$5:$G$22,7,FALSE))/1000000,0) | O12: =N12*ClaudeFxRate
A13: 46038 | B13: planning | C13: architecture | F13: claude-opus-5-5 | G13: claude-opus-5-5 | H13: 39 | I13: 7111 | J13: 91111 | K13: 433333 | L13: 7577777 | M13: 100555 | N13: =IFERROR((I13*VLOOKUP($G13,'Claude Prices'!$A$5:$G$22,3,FALSE)+J13*VLOOKUP($G13,'Claude Prices'!$A$5:$G$22,4,FALSE)+K13*VLOOKUP($G13,'Claude Prices'!$A$5:$G$22,5,FALSE)+L13*VLOOKUP($G13,'Claude Prices'!$A$5:$G$22,6,FALSE)+M13*VLOOKUP($G13,'Claude Prices'!$A$5:$G$22,7,FALSE))/1000000,0) | O13: =N13*ClaudeFxRate
A14: 46041 | B14: planning | C14: UX design | F14: claude-sonnet-5 | G14: claude-sonnet-5 | H14: 32 | I14: 6000 | J14: 82000 | K14: 300000 | L14: 4960000 | M14: 84000 | N14: =IFERROR((I14*VLOOKUP($G14,'Claude Prices'!$A$5:$G$22,3,FALSE)+J14*VLOOKUP($G14,'Claude Prices'!$A$5:$G$22,4,FALSE)+K14*VLOOKUP($G14,'Claude Prices'!$A$5:$G$22,5,FALSE)+L14*VLOOKUP($G14,'Claude Prices'!$A$5:$G$22,6,FALSE)+M14*VLOOKUP($G14,'Claude Prices'!$A$5:$G$22,7,FALSE))/1000000,0) | O14: =N14*ClaudeFxRate
A15: 46041 | B15: planning | C15: architecture | F15: claude-opus-5-5 | G15: claude-opus-5-5 | H15: 39 | I15: 7111 | J15: 91111 | K15: 433333 | L15: 7577777 | M15: 100555 | N15: =IFERROR((I15*VLOOKUP($G15,'Claude Prices'!$A$5:$G$22,3,FALSE)+J15*VLOOKUP($G15,'Claude Prices'!$A$5:$G$22,4,FALSE)+K15*VLOOKUP($G15,'Claude Prices'!$A$5:$G$22,5,FALSE)+L15*VLOOKUP($G15,'Claude Prices'!$A$5:$G$22,6,FALSE)+M15*VLOOKUP($G15,'Claude Prices'!$A$5:$G$22,7,FALSE))/1000000,0) | O15: =N15*ClaudeFxRate
A16: 46042 | B16: planning | C16: UX design | F16: claude-sonnet-5 | G16: claude-sonnet-5 | H16: 32 | I16: 6000 | J16: 82000 | K16: 300000 | L16: 4960000 | M16: 84000 | N16: =IFERROR((I16*VLOOKUP($G16,'Claude Prices'!$A$5:$G$22,3,FALSE)+J16*VLOOKUP($G16,'Claude Prices'!$A$5:$G$22,4,FALSE)+K16*VLOOKUP($G16,'Claude Prices'!$A$5:$G$22,5,FALSE)+L16*VLOOKUP($G16,'Claude Prices'!$A$5:$G$22,6,FALSE)+M16*VLOOKUP($G16,'Claude Prices'!$A$5:$G$22,7,FALSE))/1000000,0) | O16: =N16*ClaudeFxRate
... A51: 46073 | B51: planning | C51: governance (Jules) | F51: claude-opus-5-5 | G51: claude-opus-5-5 | H51: 19 | I51: 625 | J51: 8750 | K51: 31682 | L51: 520841 | M51: 7500 | N51: =IFERROR((I51*VLOOKUP($G51,'Claude Prices'!$A$5:$G$22,3,FALSE)+J51*VLOOKUP($G51,'Claude Prices'!$A$5:$G$22,4,FALSE)+K51*VLOOKUP($G51,'Claude Prices'!$A$5:$G$22,5,FALSE)+L51*VLOOKUP($G51,'Claude Prices'!$A$5:$G$22,6,FALSE)+M51*VLOOKUP($G51,'Claude Prices'!$A$5:$G$22,7,FALSE))/1000000,0) | O51: =N51*ClaudeFxRate
A52: 46083 | B52: story | C52: FAL-11 | D52: 1.1 | E52: Sign in with Entra ID | F52: claude-sonnet-5 | G52: claude-sonnet-5 | H52: 17 | I52: 3333 | J52: 41666 | K52: 175000 | L52: 2825000 | M52: 43333 | N52: =IFERROR((I52*VLOOKUP($G52,'Claude Prices'!$A$5:$G$22,3,FALSE)+J52*VLOOKUP($G52,'Claude Prices'!$A$5:$G$22,4,FALSE)+K52*VLOOKUP($G52,'Claude Prices'!$A$5:$G$22,5,FALSE)+L52*VLOOKUP($G52,'Claude Prices'!$A$5:$G$22,6,FALSE)+M52*VLOOKUP($G52,'Claude Prices'!$A$5:$G$22,7,FALSE))/1000000,0) | O52: =N52*ClaudeFxRate
A53: 46083 | B53: ops | C53: merges, promotions & deploys | F53: claude-haiku-4-5-20251001 | G53: claude-haiku-4-5 | H53: 1 | I53: 294 | J53: 1294 | K53: 4941 | L53: 101176 | M53: 1117 | N53: =IFERROR((I53*VLOOKUP($G53,'Claude Prices'!$A$5:$G$22,3,FALSE)+J53*VLOOKUP($G53,'Claude Prices'!$A$5:$G$22,4,FALSE)+K53*VLOOKUP($G53,'Claude Prices'!$A$5:$G$22,5,FALSE)+L53*VLOOKUP($G53,'Claude Prices'!$A$5:$G$22,6,FALSE)+M53*VLOOKUP($G53,'Claude Prices'!$A$5:$G$22,7,FALSE))/1000000,0) | O53: =N53*ClaudeFxRate
A54: 46084 | B54: story | C54: FAL-11 | D54: 1.1 | E54: Sign in with Entra ID | F54: claude-sonnet-5 | G54: claude-sonnet-5 | H54: 17 | I54: 3333 | J54: 41666 | K54: 175000 | L54: 2825000 | M54: 43333 | N54: =IFERROR((I54*VLOOKUP($G54,'Claude Prices'!$A$5:$G$22,3,FALSE)+J54*VLOOKUP($G54,'Claude Prices'!$A$5:$G$22,4,FALSE)+K54*VLOOKUP($G54,'Claude Prices'!$A$5:$G$22,5,FALSE)+L54*VLOOKUP($G54,'Claude Prices'!$A$5:$G$22,6,FALSE)+M54*VLOOKUP($G54,'Claude Prices'!$A$5:$G$22,7,FALSE))/1000000,0) | O54: =N54*ClaudeFxRate
A55: 46084 | B55: ops | C55: merges, promotions & deploys | F55: claude-haiku-4-5-20251001 | G55: claude-haiku-4-5 | H55: 1 | I55: 294 | J55: 1294 | K55: 4941 | L55: 101176 | M55: 1117 | N55: =IFERROR((I55*VLOOKUP($G55,'Claude Prices'!$A$5:$G$22,3,FALSE)+J55*VLOOKUP($G55,'Claude Prices'!$A$5:$G$22,4,FALSE)+K55*VLOOKUP($G55,'Claude Prices'!$A$5:$G$22,5,FALSE)+L55*VLOOKUP($G55,'Claude Prices'!$A$5:$G$22,6,FALSE)+M55*VLOOKUP($G55,'Claude Prices'!$A$5:$G$22,7,FALSE))/1000000,0) | O55: =N55*ClaudeFxRate
A56: 46085 | B56: story | C56: FAL-11 | D56: 1.1 | E56: Sign in with Entra ID | F56: claude-sonnet-5 | G56: claude-sonnet-5 | H56: 17 | I56: 3333 | J56: 41666 | K56: 175000 | L56: 2825000 | M56: 43333 | N56: =IFERROR((I56*VLOOKUP($G56,'Claude Prices'!$A$5:$G$22,3,FALSE)+J56*VLOOKUP($G56,'Claude Prices'!$A$5:$G$22,4,FALSE)+K56*VLOOKUP($G56,'Claude Prices'!$A$5:$G$22,5,FALSE)+L56*VLOOKUP($G56,'Claude Prices'!$A$5:$G$22,6,FALSE)+M56*VLOOKUP($G56,'Claude Prices'!$A$5:$G$22,7,FALSE))/1000000,0) | O56: =N56*ClaudeFxRate
A57: 46085 | B57: ops | C57: merges, promotions & deploys | F57: claude-haiku-4-5-20251001 | G57: claude-haiku-4-5 | H57: 1 | I57: 294 | J57: 1294 | K57: 4941 | L57: 101176 | M57: 1117 | N57: =IFERROR((I57*VLOOKUP($G57,'Claude Prices'!$A$5:$G$22,3,FALSE)+J57*VLOOKUP($G57,'Claude Prices'!$A$5:$G$22,4,FALSE)+K57*VLOOKUP($G57,'Claude Prices'!$A$5:$G$22,5,FALSE)+L57*VLOOKUP($G57,'Claude Prices'!$A$5:$G$22,6,FALSE)+M57*VLOOKUP($G57,'Claude Prices'!$A$5:$G$22,7,FALSE))/1000000,0) | O57: =N57*ClaudeFxRate
A58: 46086 | B58: story | C58: FAL-11 | D58: 1.1 | E58: Sign in with Entra ID | F58: claude-sonnet-5 | G58: claude-sonnet-5 | H58: 17 | I58: 3333 | J58: 41666 | K58: 175000 | L58: 2825000 | M58: 43333 | N58: =IFERROR((I58*VLOOKUP($G58,'Claude Prices'!$A$5:$G$22,3,FALSE)+J58*VLOOKUP($G58,'Claude Prices'!$A$5:$G$22,4,FALSE)+K58*VLOOKUP($G58,'Claude Prices'!$A$5:$G$22,5,FALSE)+L58*VLOOKUP($G58,'Claude Prices'!$A$5:$G$22,6,FALSE)+M58*VLOOKUP($G58,'Claude Prices'!$A$5:$G$22,7,FALSE))/1000000,0) | O58: =N58*ClaudeFxRate
A59: 46086 | B59: ops | C59: merges, promotions & deploys | F59: claude-haiku-4-5-20251001 | G59: claude-haiku-4-5 | H59: 1 | I59: 294 | J59: 1294 | K59: 4941 | L59: 101176 | M59: 1117 | N59: =IFERROR((I59*VLOOKUP($G59,'Claude Prices'!$A$5:$G$22,3,FALSE)+J59*VLOOKUP($G59,'Claude Prices'!$A$5:$G$22,4,FALSE)+K59*VLOOKUP($G59,'Claude Prices'!$A$5:$G$22,5,FALSE)+L59*VLOOKUP($G59,'Claude Prices'!$A$5:$G$22,6,FALSE)+M59*VLOOKUP($G59,'Claude Prices'!$A$5:$G$22,7,FALSE))/1000000,0) | O59: =N59*ClaudeFxRate
A60: 46087 | B60: story | C60: FAL-11 | D60: 1.1 | E60: Sign in with Entra ID | F60: claude-sonnet-5 | G60: claude-sonnet-5 | H60: 17 | I60: 3333 | J60: 41666 | K60: 175000 | L60: 2825000 | M60: 43333 | N60: =IFERROR((I60*VLOOKUP($G60,'Claude Prices'!$A$5:$G$22,3,FALSE)+J60*VLOOKUP($G60,'Claude Prices'!$A$5:$G$22,4,FALSE)+K60*VLOOKUP($G60,'Claude Prices'!$A$5:$G$22,5,FALSE)+L60*VLOOKUP($G60,'Claude Prices'!$A$5:$G$22,6,FALSE)+M60*VLOOKUP($G60,'Claude Prices'!$A$5:$G$22,7,FALSE))/1000000,0) | O60: =N60*ClaudeFxRate
A61: 46087 | B61: ops | C61: merges, promotions & deploys | F61: claude-haiku-4-5-20251001 | G61: claude-haiku-4-5 | H61: 1 | I61: 294 | J61: 1294 | K61: 4941 | L61: 101176 | M61: 1117 | N61: =IFERROR((I61*VLOOKUP($G61,'Claude Prices'!$A$5:$G$22,3,FALSE)+J61*VLOOKUP($G61,'Claude Prices'!$A$5:$G$22,4,FALSE)+K61*VLOOKUP($G61,'Claude Prices'!$A$5:$G$22,5,FALSE)+L61*VLOOKUP($G61,'Claude Prices'!$A$5:$G$22,6,FALSE)+M61*VLOOKUP($G61,'Claude Prices'!$A$5:$G$22,7,FALSE))/1000000,0) | O61: =N61*ClaudeFxRate
A62: 46090 | B62: story | C62: FAL-11 | D62: 1.1 | E62: Sign in with Entra ID | F62: claude-sonnet-5 | G62: claude-sonnet-5 | H62: 17 | I62: 3333 | J62: 41666 | K62: 175000 | L62: 2825000 | M62: 43333 | N62: =IFERROR((I62*VLOOKUP($G62,'Claude Prices'!$A$5:$G$22,3,FALSE)+J62*VLOOKUP($G62,'Claude Prices'!$A$5:$G$22,4,FALSE)+K62*VLOOKUP($G62,'Claude Prices'!$A$5:$G$22,5,FALSE)+L62*VLOOKUP($G62,'Claude Prices'!$A$5:$G$22,6,FALSE)+M62*VLOOKUP($G62,'Claude Prices'!$A$5:$G$22,7,FALSE))/1000000,0) | O62: =N62*ClaudeFxRate
A63: 46090 | B63: ops | C63: merges, promotions & deploys | F63: claude-haiku-4-5-20251001 | G63: claude-haiku-4-5 | H63: 1 | I63: 294 | J63: 1294 | K63: 4941 | L63: 101176 | M63: 1117 | N63: =IFERROR((I63*VLOOKUP($G63,'Claude Prices'!$A$5:$G$22,3,FALSE)+J63*VLOOKUP($G63,'Claude Prices'!$A$5:$G$22,4,FALSE)+K63*VLOOKUP($G63,'Claude Prices'!$A$5:$G$22,5,FALSE)+L63*VLOOKUP($G63,'Claude Prices'!$A$5:$G$22,6,FALSE)+M63*VLOOKUP($G63,'Claude Prices'!$A$5:$G$22,7,FALSE))/1000000,0) | O63: =N63*ClaudeFxRate
A64: 46091 | B64: story | C64: FAL-11 | D64: 1.1 | E64: Sign in with Entra ID | F64: claude-sonnet-5 | G64: claude-sonnet-5 | H64: 17 | I64: 3333 | J64: 41666 | K64: 175000 | L64: 2825000 | M64: 43333 | N64: =IFERROR((I64*VLOOKUP($G64,'Claude Prices'!$A$5:$G$22,3,FALSE)+J64*VLOOKUP($G64,'Claude Prices'!$A$5:$G$22,4,FALSE)+K64*VLOOKUP($G64,'Claude Prices'!$A$5:$G$22,5,FALSE)+L64*VLOOKUP($G64,'Claude Prices'!$A$5:$G$22,6,FALSE)+M64*VLOOKUP($G64,'Claude Prices'!$A$5:$G$22,7,FALSE))/1000000,0) | O64: =N64*ClaudeFxRate
A65: 46091 | B65: ops | C65: merges, promotions & deploys | F65: claude-haiku-4-5-20251001 | G65: claude-haiku-4-5 | H65: 1 | I65: 294 | J65: 1294 | K65: 4941 | L65: 101176 | M65: 1117 | N65: =IFERROR((I65*VLOOKUP($G65,'Claude Prices'!$A$5:$G$22,3,FALSE)+J65*VLOOKUP($G65,'Claude Prices'!$A$5:$G$22,4,FALSE)+K65*VLOOKUP($G65,'Claude Prices'!$A$5:$G$22,5,FALSE)+L65*VLOOKUP($G65,'Claude Prices'!$A$5:$G$22,6,FALSE)+M65*VLOOKUP($G65,'Claude Prices'!$A$5:$G$22,7,FALSE))/1000000,0) | O65: =N65*ClaudeFxRate
A66: 46092 | B66: story | C66: FAL-11 | D66: 1.1 | E66: Sign in with Entra ID | F66: claude-sonnet-5 | G66: claude-sonnet-5 | H66: 17 | I66: 3333 | J66: 41666 | K66: 175000 | L66: 2825000 | M66: 43333 | N66: =IFERROR((I66*VLOOKUP($G66,'Claude Prices'!$A$5:$G$22,3,FALSE)+J66*VLOOKUP($G66,'Claude Prices'!$A$5:$G$22,4,FALSE)+K66*VLOOKUP($G66,'Claude Prices'!$A$5:$G$22,5,FALSE)+L66*VLOOKUP($G66,'Claude Prices'!$A$5:$G$22,6,FALSE)+M66*VLOOKUP($G66,'Claude Prices'!$A$5:$G$22,7,FALSE))/1000000,0) | O66: =N66*ClaudeFxRate
A67: 46092 | B67: ops | C67: merges, promotions & deploys | F67: claude-haiku-4-5-20251001 | G67: claude-haiku-4-5 | H67: 1 | I67: 294 | J67: 1294 | K67: 4941 | L67: 101176 | M67: 1117 | N67: =IFERROR((I67*VLOOKUP($G67,'Claude Prices'!$A$5:$G$22,3,FALSE)+J67*VLOOKUP($G67,'Claude Prices'!$A$5:$G$22,4,FALSE)+K67*VLOOKUP($G67,'Claude Prices'!$A$5:$G$22,5,FALSE)+L67*VLOOKUP($G67,'Claude Prices'!$A$5:$G$22,6,FALSE)+M67*VLOOKUP($G67,'Claude Prices'!$A$5:$G$22,7,FALSE))/1000000,0) | O67: =N67*ClaudeFxRate
A68: 46093 | B68: story | C68: FAL-11 | D68: 1.1 | E68: Sign in with Entra ID | F68: claude-sonnet-5 | G68: claude-sonnet-5 | H68: 17 | I68: 3333 | J68: 41666 | K68: 175000 | L68: 2825000 | M68: 43333 | N68: =IFERROR((I68*VLOOKUP($G68,'Claude Prices'!$A$5:$G$22,3,FALSE)+J68*VLOOKUP($G68,'Claude Prices'!$A$5:$G$22,4,FALSE)+K68*VLOOKUP($G68,'Claude Prices'!$A$5:$G$22,5,FALSE)+L68*VLOOKUP($G68,'Claude Prices'!$A$5:$G$22,6,FALSE)+M68*VLOOKUP($G68,'Claude Prices'!$A$5:$G$22,7,FALSE))/1000000,0) | O68: =N68*ClaudeFxRate
A69: 46093 | B69: ops | C69: merges, promotions & deploys | F69: claude-haiku-4-5-20251001 | G69: claude-haiku-4-5 | H69: 1 | I69: 294 | J69: 1294 | K69: 4941 | L69: 101176 | M69: 1117 | N69: =IFERROR((I69*VLOOKUP($G69,'Claude Prices'!$A$5:$G$22,3,FALSE)+J69*VLOOKUP($G69,'Claude Prices'!$A$5:$G$22,4,FALSE)+K69*VLOOKUP($G69,'Claude Prices'!$A$5:$G$22,5,FALSE)+L69*VLOOKUP($G69,'Claude Prices'!$A$5:$G$22,6,FALSE)+M69*VLOOKUP($G69,'Claude Prices'!$A$5:$G$22,7,FALSE))/1000000,0) | O69: =N69*ClaudeFxRate
A70: 46094 | B70: story | C70: FAL-11 | D70: 1.1 | E70: Sign in with Entra ID | F70: claude-sonnet-5 | G70: claude-sonnet-5 | H70: 17 | I70: 3333 | J70: 41666 | K70: 175000 | L70: 2825000 | M70: 43333 | N70: =IFERROR((I70*VLOOKUP($G70,'Claude Prices'!$A$5:$G$22,3,FALSE)+J70*VLOOKUP($G70,'Claude Prices'!$A$5:$G$22,4,FALSE)+K70*VLOOKUP($G70,'Claude Prices'!$A$5:$G$22,5,FALSE)+L70*VLOOKUP($G70,'Claude Prices'!$A$5:$G$22,6,FALSE)+M70*VLOOKUP($G70,'Claude Prices'!$A$5:$G$22,7,FALSE))/1000000,0) | O70: =N70*ClaudeFxRate
A71: 46094 | B71: ops | C71: merges, promotions & deploys | F71: claude-haiku-4-5-20251001 | G71: claude-haiku-4-5 | H71: 1 | I71: 294 | J71: 1294 | K71: 4941 | L71: 101176 | M71: 1117 | N71: =IFERROR((I71*VLOOKUP($G71,'Claude Prices'!$A$5:$G$22,3,FALSE)+J71*VLOOKUP($G71,'Claude Prices'!$A$5:$G$22,4,FALSE)+K71*VLOOKUP($G71,'Claude Prices'!$A$5:$G$22,5,FALSE)+L71*VLOOKUP($G71,'Claude Prices'!$A$5:$G$22,6,FALSE)+M71*VLOOKUP($G71,'Claude Prices'!$A$5:$G$22,7,FALSE))/1000000,0) | O71: =N71*ClaudeFxRate
A72: 46097 | B72: story | C72: FAL-11 | D72: 1.1 | E72: Sign in with Entra ID | F72: claude-sonnet-5 | G72: claude-sonnet-5 | H72: 17 | I72: 3333 | J72: 41666 | K72: 175000 | L72: 2825000 | M72: 43333 | N72: =IFERROR((I72*VLOOKUP($G72,'Claude Prices'!$A$5:$G$22,3,FALSE)+J72*VLOOKUP($G72,'Claude Prices'!$A$5:$G$22,4,FALSE)+K72*VLOOKUP($G72,'Claude Prices'!$A$5:$G$22,5,FALSE)+L72*VLOOKUP($G72,'Claude Prices'!$A$5:$G$22,6,FALSE)+M72*VLOOKUP($G72,'Claude Prices'!$A$5:$G$22,7,FALSE))/1000000,0) | O72: =N72*ClaudeFxRate
A73: 46097 | B73: ops | C73: merges, promotions & deploys | F73: claude-haiku-4-5-20251001 | G73: claude-haiku-4-5 | H73: 1 | I73: 294 | J73: 1294 | K73: 4941 | L73: 101176 | M73: 1117 | N73: =IFERROR((I73*VLOOKUP($G73,'Claude Prices'!$A$5:$G$22,3,FALSE)+J73*VLOOKUP($G73,'Claude Prices'!$A$5:$G$22,4,FALSE)+K73*VLOOKUP($G73,'Claude Prices'!$A$5:$G$22,5,FALSE)+L73*VLOOKUP($G73,'Claude Prices'!$A$5:$G$22,6,FALSE)+M73*VLOOKUP($G73,'Claude Prices'!$A$5:$G$22,7,FALSE))/1000000,0) | O73: =N73*ClaudeFxRate
A74: 46098 | B74: story | C74: FAL-11 | D74: 1.1 | E74: Sign in with Entra ID | F74: claude-sonnet-5 | G74: claude-sonnet-5 | H74: 25 | I74: 3337 | J74: 41674 | K74: 175000 | L74: 2825000 | M74: 43337 | N74: =IFERROR((I74*VLOOKUP($G74,'Claude Prices'!$A$5:$G$22,3,FALSE)+J74*VLOOKUP($G74,'Claude Prices'!$A$5:$G$22,4,FALSE)+K74*VLOOKUP($G74,'Claude Prices'!$A$5:$G$22,5,FALSE)+L74*VLOOKUP($G74,'Claude Prices'!$A$5:$G$22,6,FALSE)+M74*VLOOKUP($G74,'Claude Prices'!$A$5:$G$22,7,FALSE))/1000000,0) | O74: =N74*ClaudeFxRate
A75: 46098 | B75: ops | C75: merges, promotions & deploys | F75: claude-haiku-4-5-20251001 | G75: claude-haiku-4-5 | H75: 1 | I75: 294 | J75: 1294 | K75: 4941 | L75: 101176 | M75: 1117 | N75: =IFERROR((I75*VLOOKUP($G75,'Claude Prices'!$A$5:$G$22,3,FALSE)+J75*VLOOKUP($G75,'Claude Prices'!$A$5:$G$22,4,FALSE)+K75*VLOOKUP($G75,'Claude Prices'!$A$5:$G$22,5,FALSE)+L75*VLOOKUP($G75,'Claude Prices'!$A$5:$G$22,6,FALSE)+M75*VLOOKUP($G75,'Claude Prices'!$A$5:$G$22,7,FALSE))/1000000,0) | O75: =N75*ClaudeFxRate
A76: 46099 | B76: story | C76: FAL-12 | D76: 1.2 | E76: Start an application | F76: claude-sonnet-5 | G76: claude-sonnet-5 | H76: 25 | I76: 4750 | J76: 60000 | K76: 250000 | L76: 4058333 | M76: 63333 | N76: =IFERROR((I76*VLOOKUP($G76,'Claude Prices'!$A$5:$G$22,3,FALSE)+J76*VLOOKUP($G76,'Claude Prices'!$A$5:$G$22,4,FALSE)+K76*VLOOKUP($G76,'Claude Prices'!$A$5:$G$22,5,FALSE)+L76*VLOOKUP($G76,'Claude Prices'!$A$5:$G$22,6,FALSE)+M76*VLOOKUP($G76,'Claude Prices'!$A$5:$G$22,7,FALSE))/1000000,0) | O76: =N76*ClaudeFxRate
A77: 46099 | B77: ops | C77: merges, promotions & deploys | F77: claude-haiku-4-5-20251001 | G77: claude-haiku-4-5 | H77: 1 | I77: 294 | J77: 1294 | K77: 4941 | L77: 101176 | M77: 1117 | N77: =IFERROR((I77*VLOOKUP($G77,'Claude Prices'!$A$5:$G$22,3,FALSE)+J77*VLOOKUP($G77,'Claude Prices'!$A$5:$G$22,4,FALSE)+K77*VLOOKUP($G77,'Claude Prices'!$A$5:$G$22,5,FALSE)+L77*VLOOKUP($G77,'Claude Prices'!$A$5:$G$22,6,FALSE)+M77*VLOOKUP($G77,'Claude Prices'!$A$5:$G$22,7,FALSE))/1000000,0) | O77: =N77*ClaudeFxRate
A78: 46100 | B78: story | C78: FAL-12 | D78: 1.2 | E78: Start an application | F78: claude-sonnet-5 | G78: claude-sonnet-5 | H78: 25 | I78: 4750 | J78: 60000 | K78: 250000 | L78: 4058333 | M78: 63333 | N78: =IFERROR((I78*VLOOKUP($G78,'Claude Prices'!$A$5:$G$22,3,FALSE)+J78*VLOOKUP($G78,'Claude Prices'!$A$5:$G$22,4,FALSE)+K78*VLOOKUP($G78,'Claude Prices'!$A$5:$G$22,5,FALSE)+L78*VLOOKUP($G78,'Claude Prices'!$A$5:$G$22,6,FALSE)+M78*VLOOKUP($G78,'Claude Prices'!$A$5:$G$22,7,FALSE))/1000000,0) | O78: =N78*ClaudeFxRate
A79: 46100 | B79: ops | C79: merges, promotions & deploys | F79: claude-haiku-4-5-20251001 | G79: claude-haiku-4-5 | H79: 1 | I79: 294 | J79: 1294 | K79: 4941 | L79: 101176 | M79: 1117 | N79: =IFERROR((I79*VLOOKUP($G79,'Claude Prices'!$A$5:$G$22,3,FALSE)+J79*VLOOKUP($G79,'Claude Prices'!$A$5:$G$22,4,FALSE)+K79*VLOOKUP($G79,'Claude Prices'!$A$5:$G$22,5,FALSE)+L79*VLOOKUP($G79,'Claude Prices'!$A$5:$G$22,6,FALSE)+M79*VLOOKUP($G79,'Claude Prices'!$A$5:$G$22,7,FALSE))/1000000,0) | O79: =N79*ClaudeFxRate
A80: 46101 | B80: story | C80: FAL-12 | D80: 1.2 | E80: Start an application | F80: claude-sonnet-5 | G80: claude-sonnet-5 | H80: 25 | I80: 4750 | J80: 60000 | K80: 250000 | L80: 4058333 | M80: 63333 | N80: =IFERROR((I80*VLOOKUP($G80,'Claude Prices'!$A$5:$G$22,3,FALSE)+J80*VLOOKUP($G80,'Claude Prices'!$A$5:$G$22,4,FALSE)+K80*VLOOKUP($G80,'Claude Prices'!$A$5:$G$22,5,FALSE)+L80*VLOOKUP($G80,'Claude Prices'!$A$5:$G$22,6,FALSE)+M80*VLOOKUP($G80,'Claude Prices'!$A$5:$G$22,7,FALSE))/1000000,0) | O80: =N80*ClaudeFxRate
A81: 46101 | B81: ops | C81: merges, promotions & deploys | F81: claude-haiku-4-5-20251001 | G81: claude-haiku-4-5 | H81: 1 | I81: 294 | J81: 1294 | K81: 4941 | L81: 101176 | M81: 1117 | N81: =IFERROR((I81*VLOOKUP($G81,'Claude Prices'!$A$5:$G$22,3,FALSE)+J81*VLOOKUP($G81,'Claude Prices'!$A$5:$G$22,4,FALSE)+K81*VLOOKUP($G81,'Claude Prices'!$A$5:$G$22,5,FALSE)+L81*VLOOKUP($G81,'Claude Prices'!$A$5:$G$22,6,FALSE)+M81*VLOOKUP($G81,'Claude Prices'!$A$5:$G$22,7,FALSE))/1000000,0) | O81: =N81*ClaudeFxRate
A82: 46104 | B82: story | C82: FAL-12 | D82: 1.2 | E82: Start an application | F82: claude-sonnet-5 | G82: claude-sonnet-5 | H82: 25 | I82: 4750 | J82: 60000 | K82: 250000 | L82: 4058333 | M82: 63333 | N82: =IFERROR((I82*VLOOKUP($G82,'Claude Prices'!$A$5:$G$22,3,FALSE)+J82*VLOOKUP($G82,'Claude Prices'!$A$5:$G$22,4,FALSE)+K82*VLOOKUP($G82,'Claude Prices'!$A$5:$G$22,5,FALSE)+L82*VLOOKUP($G82,'Claude Prices'!$A$5:$G$22,6,FALSE)+M82*VLOOKUP($G82,'Claude Prices'!$A$5:$G$22,7,FALSE))/1000000,0) | O82: =N82*ClaudeFxRate
A83: 46104 | B83: ops | C83: merges, promotions & deploys | F83: claude-haiku-4-5-20251001 | G83: claude-haiku-4-5 | H83: 1 | I83: 294 | J83: 1294 | K83: 4941 | L83: 101176 | M83: 1117 | N83: =IFERROR((I83*VLOOKUP($G83,'Claude Prices'!$A$5:$G$22,3,FALSE)+J83*VLOOKUP($G83,'Claude Prices'!$A$5:$G$22,4,FALSE)+K83*VLOOKUP($G83,'Claude Prices'!$A$5:$G$22,5,FALSE)+L83*VLOOKUP($G83,'Claude Prices'!$A$5:$G$22,6,FALSE)+M83*VLOOKUP($G83,'Claude Prices'!$A$5:$G$22,7,FALSE))/1000000,0) | O83: =N83*ClaudeFxRate
A84: 46105 | B84: story | C84: FAL-12 | D84: 1.2 | E84: Start an application | F84: claude-sonnet-5 | G84: claude-sonnet-5 | H84: 25 | I84: 4750 | J84: 60000 | K84: 250000 | L84: 4058333 | M84: 63333 | N84: =IFERROR((I84*VLOOKUP($G84,'Claude Prices'!$A$5:$G$22,3,FALSE)+J84*VLOOKUP($G84,'Claude Prices'!$A$5:$G$22,4,FALSE)+K84*VLOOKUP($G84,'Claude Prices'!$A$5:$G$22,5,FALSE)+L84*VLOOKUP($G84,'Claude Prices'!$A$5:$G$22,6,FALSE)+M84*VLOOKUP($G84,'Claude Prices'!$A$5:$G$22,7,FALSE))/1000000,0) | O84: =N84*ClaudeFxRate
A85: 46105 | B85: ops | C85: merges, promotions & deploys | F85: claude-haiku-4-5-20251001 | G85: claude-haiku-4-5 | H85: 1 | I85: 294 | J85: 1294 | K85: 4941 | L85: 101176 | M85: 1117 | N85: =IFERROR((I85*VLOOKUP($G85,'Claude Prices'!$A$5:$G$22,3,FALSE)+J85*VLOOKUP($G85,'Claude Prices'!$A$5:$G$22,4,FALSE)+K85*VLOOKUP($G85,'Claude Prices'!$A$5:$G$22,5,FALSE)+L85*VLOOKUP($G85,'Claude Prices'!$A$5:$G$22,6,FALSE)+M85*VLOOKUP($G85,'Claude Prices'!$A$5:$G$22,7,FALSE))/1000000,0) | O85: =N85*ClaudeFxRate
A86: 46106 | B86: story | C86: FAL-12 | D86: 1.2 | E86: Start an application | F86: claude-sonnet-5 | G86: claude-sonnet-5 | H86: 25 | I86: 4750 | J86: 60000 | K86: 250000 | L86: 4058333 | M86: 63333 | N86: =IFERROR((I86*VLOOKUP($G86,'Claude Prices'!$A$5:$G$22,3,FALSE)+J86*VLOOKUP($G86,'Claude Prices'!$A$5:$G$22,4,FALSE)+K86*VLOOKUP($G86,'Claude Prices'!$A$5:$G$22,5,FALSE)+L86*VLOOKUP($G86,'Claude Prices'!$A$5:$G$22,6,FALSE)+M86*VLOOKUP($G86,'Claude Prices'!$A$5:$G$22,7,FALSE))/1000000,0) | O86: =N86*ClaudeFxRate
A87: 46106 | B87: ops | C87: merges, promotions & deploys | F87: claude-haiku-4-5-20251001 | G87: claude-haiku-4-5 | H87: 1 | I87: 294 | J87: 1294 | K87: 4941 | L87: 101176 | M87: 1117 | N87: =IFERROR((I87*VLOOKUP($G87,'Claude Prices'!$A$5:$G$22,3,FALSE)+J87*VLOOKUP($G87,'Claude Prices'!$A$5:$G$22,4,FALSE)+K87*VLOOKUP($G87,'Claude Prices'!$A$5:$G$22,5,FALSE)+L87*VLOOKUP($G87,'Claude Prices'!$A$5:$G$22,6,FALSE)+M87*VLOOKUP($G87,'Claude Prices'!$A$5:$G$22,7,FALSE))/1000000,0) | O87: =N87*ClaudeFxRate
A88: 46107 | B88: story | C88: FAL-12 | D88: 1.2 | E88: Start an application | F88: claude-sonnet-5 | G88: claude-sonnet-5 | H88: 25 | I88: 4750 | J88: 60000 | K88: 250000 | L88: 4058333 | M88: 63333 | N88: =IFERROR((I88*VLOOKUP($G88,'Claude Prices'!$A$5:$G$22,3,FALSE)+J88*VLOOKUP($G88,'Claude Prices'!$A$5:$G$22,4,FALSE)+K88*VLOOKUP($G88,'Claude Prices'!$A$5:$G$22,5,FALSE)+L88*VLOOKUP($G88,'Claude Prices'!$A$5:$G$22,6,FALSE)+M88*VLOOKUP($G88,'Claude Prices'!$A$5:$G$22,7,FALSE))/1000000,0) | O88: =N88*ClaudeFxRate
A89: 46107 | B89: ops | C89: merges, promotions & deploys | F89: claude-haiku-4-5-20251001 | G89: claude-haiku-4-5 | H89: 1 | I89: 294 | J89: 1294 | K89: 4941 | L89: 101176 | M89: 1117 | N89: =IFERROR((I89*VLOOKUP($G89,'Claude Prices'!$A$5:$G$22,3,FALSE)+J89*VLOOKUP($G89,'Claude Prices'!$A$5:$G$22,4,FALSE)+K89*VLOOKUP($G89,'Claude Prices'!$A$5:$G$22,5,FALSE)+L89*VLOOKUP($G89,'Claude Prices'!$A$5:$G$22,6,FALSE)+M89*VLOOKUP($G89,'Claude Prices'!$A$5:$G$22,7,FALSE))/1000000,0) | O89: =N89*ClaudeFxRate
A90: 46108 | B90: story | C90: FAL-12 | D90: 1.2 | E90: Start an application | F90: claude-sonnet-5 | G90: claude-sonnet-5 | H90: 25 | I90: 4750 | J90: 60000 | K90: 250000 | L90: 4058333 | M90: 63333 | N90: =IFERROR((I90*VLOOKUP($G90,'Claude Prices'!$A$5:$G$22,3,FALSE)+J90*VLOOKUP($G90,'Claude Prices'!$A$5:$G$22,4,FALSE)+K90*VLOOKUP($G90,'Claude Prices'!$A$5:$G$22,5,FALSE)+L90*VLOOKUP($G90,'Claude Prices'!$A$5:$G$22,6,FALSE)+M90*VLOOKUP($G90,'Claude Prices'!$A$5:$G$22,7,FALSE))/1000000,0) | O90: =N90*ClaudeFxRate
A91: 46108 | B91: ops | C91: merges, promotions & deploys | F91: claude-haiku-4-5-20251001 | G91: claude-haiku-4-5 | H91: 1 | I91: 294 | J91: 1294 | K91: 4941 | L91: 101176 | M91: 1117 | N91: =IFERROR((I91*VLOOKUP($G91,'Claude Prices'!$A$5:$G$22,3,FALSE)+J91*VLOOKUP($G91,'Claude Prices'!$A$5:$G$22,4,FALSE)+K91*VLOOKUP($G91,'Claude Prices'!$A$5:$G$22,5,FALSE)+L91*VLOOKUP($G91,'Claude Prices'!$A$5:$G$22,6,FALSE)+M91*VLOOKUP($G91,'Claude Prices'!$A$5:$G$22,7,FALSE))/1000000,0) | O91: =N91*ClaudeFxRate
A92: 46111 | B92: story | C92: FAL-12 | D92: 1.2 | E92: Start an application | F92: claude-sonnet-5 | G92: claude-sonnet-5 | H92: 25 | I92: 4750 | J92: 60000 | K92: 250000 | L92: 4058333 | M92: 63333 | N92: =IFERROR((I92*VLOOKUP($G92,'Claude Prices'!$A$5:$G$22,3,FALSE)+J92*VLOOKUP($G92,'Claude Prices'!$A$5:$G$22,4,FALSE)+K92*VLOOKUP($G92,'Claude Prices'!$A$5:$G$22,5,FALSE)+L92*VLOOKUP($G92,'Claude Prices'!$A$5:$G$22,6,FALSE)+M92*VLOOKUP($G92,'Claude Prices'!$A$5:$G$22,7,FALSE))/1000000,0) | O92: =N92*ClaudeFxRate
A93: 46111 | B93: ops | C93: merges, promotions & deploys | F93: claude-haiku-4-5-20251001 | G93: claude-haiku-4-5 | H93: 1 | I93: 294 | J93: 1294 | K93: 4941 | L93: 101176 | M93: 1117 | N93: =IFERROR((I93*VLOOKUP($G93,'Claude Prices'!$A$5:$G$22,3,FALSE)+J93*VLOOKUP($G93,'Claude Prices'!$A$5:$G$22,4,FALSE)+K93*VLOOKUP($G93,'Claude Prices'!$A$5:$G$22,5,FALSE)+L93*VLOOKUP($G93,'Claude Prices'!$A$5:$G$22,6,FALSE)+M93*VLOOKUP($G93,'Claude Prices'!$A$5:$G$22,7,FALSE))/1000000,0) | O93: =N93*ClaudeFxRate
A94: 46112 | B94: story | C94: FAL-12 | D94: 1.2 | E94: Start an application | F94: claude-sonnet-5 | G94: claude-sonnet-5 | H94: 25 | I94: 4750 | J94: 60000 | K94: 250000 | L94: 4058333 | M94: 63333 | N94: =IFERROR((I94*VLOOKUP($G94,'Claude Prices'!$A$5:$G$22,3,FALSE)+J94*VLOOKUP($G94,'Claude Prices'!$A$5:$G$22,4,FALSE)+K94*VLOOKUP($G94,'Claude Prices'!$A$5:$G$22,5,FALSE)+L94*VLOOKUP($G94,'Claude Prices'!$A$5:$G$22,6,FALSE)+M94*VLOOKUP($G94,'Claude Prices'!$A$5:$G$22,7,FALSE))/1000000,0) | O94: =N94*ClaudeFxRate
A95: 46112 | B95: ops | C95: merges, promotions & deploys | F95: claude-haiku-4-5-20251001 | G95: claude-haiku-4-5 | H95: 1 | I95: 294 | J95: 1294 | K95: 4941 | L95: 101176 | M95: 1117 | N95: =IFERROR((I95*VLOOKUP($G95,'Claude Prices'!$A$5:$G$22,3,FALSE)+J95*VLOOKUP($G95,'Claude Prices'!$A$5:$G$22,4,FALSE)+K95*VLOOKUP($G95,'Claude Prices'!$A$5:$G$22,5,FALSE)+L95*VLOOKUP($G95,'Claude Prices'!$A$5:$G$22,6,FALSE)+M95*VLOOKUP($G95,'Claude Prices'!$A$5:$G$22,7,FALSE))/1000000,0) | O95: =N95*ClaudeFxRate
A96: 46113 | B96: story | C96: FAL-12 | D96: 1.2 | E96: Start an application | F96: claude-sonnet-5 | G96: claude-sonnet-5 | H96: 25 | I96: 4750 | J96: 60000 | K96: 250000 | L96: 4058333 | M96: 63333 | N96: =IFERROR((I96*VLOOKUP($G96,'Claude Prices'!$A$5:$G$22,3,FALSE)+J96*VLOOKUP($G96,'Claude Prices'!$A$5:$G$22,4,FALSE)+K96*VLOOKUP($G96,'Claude Prices'!$A$5:$G$22,5,FALSE)+L96*VLOOKUP($G96,'Claude Prices'!$A$5:$G$22,6,FALSE)+M96*VLOOKUP($G96,'Claude Prices'!$A$5:$G$22,7,FALSE))/1000000,0) | O96: =N96*ClaudeFxRate
A97: 46113 | B97: ops | C97: merges, promotions & deploys | F97: claude-haiku-4-5-20251001 | G97: claude-haiku-4-5 | H97: 1 | I97: 294 | J97: 1294 | K97: 4941 | L97: 101176 | M97: 1117 | N97: =IFERROR((I97*VLOOKUP($G97,'Claude Prices'!$A$5:$G$22,3,FALSE)+J97*VLOOKUP($G97,'Claude Prices'!$A$5:$G$22,4,FALSE)+K97*VLOOKUP($G97,'Claude Prices'!$A$5:$G$22,5,FALSE)+L97*VLOOKUP($G97,'Claude Prices'!$A$5:$G$22,6,FALSE)+M97*VLOOKUP($G97,'Claude Prices'!$A$5:$G$22,7,FALSE))/1000000,0) | O97: =N97*ClaudeFxRate
A98: 46114 | B98: story | C98: FAL-12 | D98: 1.2 | E98: Start an application | F98: claude-sonnet-5 | G98: claude-sonnet-5 | H98: 30 | I98: 4750 | J98: 60000 | K98: 250000 | L98: 4058337 | M98: 63337 | N98: =IFERROR((I98*VLOOKUP($G98,'Claude Prices'!$A$5:$G$22,3,FALSE)+J98*VLOOKUP($G98,'Claude Prices'!$A$5:$G$22,4,FALSE)+K98*VLOOKUP($G98,'Claude Prices'!$A$5:$G$22,5,FALSE)+L98*VLOOKUP($G98,'Claude Prices'!$A$5:$G$22,6,FALSE)+M98*VLOOKUP($G98,'Claude Prices'!$A$5:$G$22,7,FALSE))/1000000,0) | O98: =N98*ClaudeFxRate
A99: 46114 | B99: ops | C99: merges, promotions & deploys | F99: claude-haiku-4-5-20251001 | G99: claude-haiku-4-5 | H99: 1 | I99: 294 | J99: 1294 | K99: 4941 | L99: 101176 | M99: 1117 | N99: =IFERROR((I99*VLOOKUP($G99,'Claude Prices'!$A$5:$G$22,3,FALSE)+J99*VLOOKUP($G99,'Claude Prices'!$A$5:$G$22,4,FALSE)+K99*VLOOKUP($G99,'Claude Prices'!$A$5:$G$22,5,FALSE)+L99*VLOOKUP($G99,'Claude Prices'!$A$5:$G$22,6,FALSE)+M99*VLOOKUP($G99,'Claude Prices'!$A$5:$G$22,7,FALSE))/1000000,0) | O99: =N99*ClaudeFxRate
A100: 46115 | B100: story | C100: FAL-13 | D100: 1.3 | E100: Upload documents | F100: claude-haiku-4-5-20251001 | G100: claude-haiku-4-5 | H100: 8 | I100: 1500 | J100: 7500 | K100: 25000 | L100: 516666 | M100: 5833 | N100: =IFERROR((I100*VLOOKUP($G100,'Claude Prices'!$A$5:$G$22,3,FALSE)+J100*VLOOKUP($G100,'Claude Prices'!$A$5:$G$22,4,FALSE)+K100*VLOOKUP($G100,'Claude Prices'!$A$5:$G$22,5,FALSE)+L100*VLOOKUP($G100,'Claude Prices'!$A$5:$G$22,6,FALSE)+M100*VLOOKUP($G100,'Claude Prices'!$A$5:$G$22,7,FALSE))/1000000,0) | O100: =N100*ClaudeFxRate
A101: 46115 | B101: story | C101: FAL-13 | D101: 1.3 | E101: Upload documents | F101: claude-sonnet-5 | G101: claude-sonnet-5 | H101: 20 | I101: 3833 | J101: 50000 | K101: 208333 | L101: 3341666 | M101: 50833 | N101: =IFERROR((I101*VLOOKUP($G101,'Claude Prices'!$A$5:$G$22,3,FALSE)+J101*VLOOKUP($G101,'Claude Prices'!$A$5:$G$22,4,FALSE)+K101*VLOOKUP($G101,'Claude Prices'!$A$5:$G$22,5,FALSE)+L101*VLOOKUP($G101,'Claude Prices'!$A$5:$G$22,6,FALSE)+M101*VLOOKUP($G101,'Claude Prices'!$A$5:$G$22,7,FALSE))/1000000,0) | O101: =N101*ClaudeFxRate
A102: 46115 | B102: ops | C102: merges, promotions & deploys | F102: claude-haiku-4-5-20251001 | G102: claude-haiku-4-5 | H102: 1 | I102: 294 | J102: 1294 | K102: 4941 | L102: 101176 | M102: 1117 | N102: =IFERROR((I102*VLOOKUP($G102,'Claude Prices'!$A$5:$G$22,3,FALSE)+J102*VLOOKUP($G102,'Claude Prices'!$A$5:$G$22,4,FALSE)+K102*VLOOKUP($G102,'Claude Prices'!$A$5:$G$22,5,FALSE)+L102*VLOOKUP($G102,'Claude Prices'!$A$5:$G$22,6,FALSE)+M102*VLOOKUP($G102,'Claude Prices'!$A$5:$G$22,7,FALSE))/1000000,0) | O102: =N102*ClaudeFxRate
A103: 46118 | B103: story | C103: FAL-13 | D103: 1.3 | E103: Upload documents | F103: claude-haiku-4-5-20251001 | G103: claude-haiku-4-5 | H103: 8 | I103: 1500 | J103: 7500 | K103: 25000 | L103: 516666 | M103: 5833 | N103: =IFERROR((I103*VLOOKUP($G103,'Claude Prices'!$A$5:$G$22,3,FALSE)+J103*VLOOKUP($G103,'Claude Prices'!$A$5:$G$22,4,FALSE)+K103*VLOOKUP($G103,'Claude Prices'!$A$5:$G$22,5,FALSE)+L103*VLOOKUP($G103,'Claude Prices'!$A$5:$G$22,6,FALSE)+M103*VLOOKUP($G103,'Claude Prices'!$A$5:$G$22,7,FALSE))/1000000,0) | O103: =N103*ClaudeFxRate
A104: 46118 | B104: story | C104: FAL-13 | D104: 1.3 | E104: Upload documents | F104: claude-sonnet-5 | G104: claude-sonnet-5 | H104: 20 | I104: 3833 | J104: 50000 | K104: 208333 | L104: 3341666 | M104: 50833 | N104: =IFERROR((I104*VLOOKUP($G104,'Claude Prices'!$A$5:$G$22,3,FALSE)+J104*VLOOKUP($G104,'Claude Prices'!$A$5:$G$22,4,FALSE)+K104*VLOOKUP($G104,'Claude Prices'!$A$5:$G$22,5,FALSE)+L104*VLOOKUP($G104,'Claude Prices'!$A$5:$G$22,6,FALSE)+M104*VLOOKUP($G104,'Claude Prices'!$A$5:$G$22,7,FALSE))/1000000,0) | O104: =N104*ClaudeFxRate
A105: 46118 | B105: ops | C105: merges, promotions & deploys | F105: claude-haiku-4-5-20251001 | G105: claude-haiku-4-5 | H105: 1 | I105: 294 | J105: 1294 | K105: 4941 | L105: 101176 | M105: 1117 | N105: =IFERROR((I105*VLOOKUP($G105,'Claude Prices'!$A$5:$G$22,3,FALSE)+J105*VLOOKUP($G105,'Claude Prices'!$A$5:$G$22,4,FALSE)+K105*VLOOKUP($G105,'Claude Prices'!$A$5:$G$22,5,FALSE)+L105*VLOOKUP($G105,'Claude Prices'!$A$5:$G$22,6,FALSE)+M105*VLOOKUP($G105,'Claude Prices'!$A$5:$G$22,7,FALSE))/1000000,0) | O105: =N105*ClaudeFxRate
A106: 46119 | B106: story | C106: FAL-13 | D106: 1.3 | E106: Upload documents | F106: claude-haiku-4-5-20251001 | G106: claude-haiku-4-5 | H106: 8 | I106: 1500 | J106: 7500 | K106: 25000 | L106: 516666 | M106: 5833 | N106: =IFERROR((I106*VLOOKUP($G106,'Claude Prices'!$A$5:$G$22,3,FALSE)+J106*VLOOKUP($G106,'Claude Prices'!$A$5:$G$22,4,FALSE)+K106*VLOOKUP($G106,'Claude Prices'!$A$5:$G$22,5,FALSE)+L106*VLOOKUP($G106,'Claude Prices'!$A$5:$G$22,6,FALSE)+M106*VLOOKUP($G106,'Claude Prices'!$A$5:$G$22,7,FALSE))/1000000,0) | O106: =N106*ClaudeFxRate
A107: 46119 | B107: story | C107: FAL-13 | D107: 1.3 | E107: Upload documents | F107: claude-sonnet-5 | G107: claude-sonnet-5 | H107: 20 | I107: 3833 | J107: 50000 | K107: 208333 | L107: 3341666 | M107: 50833 | N107: =IFERROR((I107*VLOOKUP($G107,'Claude Prices'!$A$5:$G$22,3,FALSE)+J107*VLOOKUP($G107,'Claude Prices'!$A$5:$G$22,4,FALSE)+K107*VLOOKUP($G107,'Claude Prices'!$A$5:$G$22,5,FALSE)+L107*VLOOKUP($G107,'Claude Prices'!$A$5:$G$22,6,FALSE)+M107*VLOOKUP($G107,'Claude Prices'!$A$5:$G$22,7,FALSE))/1000000,0) | O107: =N107*ClaudeFxRate
A108: 46119 | B108: ops | C108: merges, promotions & deploys | F108: claude-haiku-4-5-20251001 | G108: claude-haiku-4-5 | H108: 1 | I108: 294 | J108: 1294 | K108: 4941 | L108: 101176 | M108: 1117 | N108: =IFERROR((I108*VLOOKUP($G108,'Claude Prices'!$A$5:$G$22,3,FALSE)+J108*VLOOKUP($G108,'Claude Prices'!$A$5:$G$22,4,FALSE)+K108*VLOOKUP($G108,'Claude Prices'!$A$5:$G$22,5,FALSE)+L108*VLOOKUP($G108,'Claude Prices'!$A$5:$G$22,6,FALSE)+M108*VLOOKUP($G108,'Claude Prices'!$A$5:$G$22,7,FALSE))/1000000,0) | O108: =N108*ClaudeFxRate
A109: 46120 | B109: story | C109: FAL-13 | D109: 1.3 | E109: Upload documents | F109: claude-haiku-4-5-20251001 | G109: claude-haiku-4-5 | H109: 8 | I109: 1500 | J109: 7500 | K109: 25000 | L109: 516666 | M109: 5833 | N109: =IFERROR((I109*VLOOKUP($G109,'Claude Prices'!$A$5:$G$22,3,FALSE)+J109*VLOOKUP($G109,'Claude Prices'!$A$5:$G$22,4,FALSE)+K109*VLOOKUP($G109,'Claude Prices'!$A$5:$G$22,5,FALSE)+L109*VLOOKUP($G109,'Claude Prices'!$A$5:$G$22,6,FALSE)+M109*VLOOKUP($G109,'Claude Prices'!$A$5:$G$22,7,FALSE))/1000000,0) | O109: =N109*ClaudeFxRate
A110: 46120 | B110: story | C110: FAL-13 | D110: 1.3 | E110: Upload documents | F110: claude-sonnet-5 | G110: claude-sonnet-5 | H110: 20 | I110: 3833 | J110: 50000 | K110: 208333 | L110: 3341666 | M110: 50833 | N110: =IFERROR((I110*VLOOKUP($G110,'Claude Prices'!$A$5:$G$22,3,FALSE)+J110*VLOOKUP($G110,'Claude Prices'!$A$5:$G$22,4,FALSE)+K110*VLOOKUP($G110,'Claude Prices'!$A$5:$G$22,5,FALSE)+L110*VLOOKUP($G110,'Claude Prices'!$A$5:$G$22,6,FALSE)+M110*VLOOKUP($G110,'Claude Prices'!$A$5:$G$22,7,FALSE))/1000000,0) | O110: =N110*ClaudeFxRate
A111: 46120 | B111: ops | C111: merges, promotions & deploys | F111: claude-haiku-4-5-20251001 | G111: claude-haiku-4-5 | H111: 1 | I111: 294 | J111: 1294 | K111: 4941 | L111: 101176 | M111: 1117 | N111: =IFERROR((I111*VLOOKUP($G111,'Claude Prices'!$A$5:$G$22,3,FALSE)+J111*VLOOKUP($G111,'Claude Prices'!$A$5:$G$22,4,FALSE)+K111*VLOOKUP($G111,'Claude Prices'!$A$5:$G$22,5,FALSE)+L111*VLOOKUP($G111,'Claude Prices'!$A$5:$G$22,6,FALSE)+M111*VLOOKUP($G111,'Claude Prices'!$A$5:$G$22,7,FALSE))/1000000,0) | O111: =N111*ClaudeFxRate
A112: 46121 | B112: story | C112: FAL-13 | D112: 1.3 | E112: Upload documents | F112: claude-haiku-4-5-20251001 | G112: claude-haiku-4-5 | H112: 8 | I112: 1500 | J112: 7500 | K112: 25000 | L112: 516666 | M112: 5833 | N112: =IFERROR((I112*VLOOKUP($G112,'Claude Prices'!$A$5:$G$22,3,FALSE)+J112*VLOOKUP($G112,'Claude Prices'!$A$5:$G$22,4,FALSE)+K112*VLOOKUP($G112,'Claude Prices'!$A$5:$G$22,5,FALSE)+L112*VLOOKUP($G112,'Claude Prices'!$A$5:$G$22,6,FALSE)+M112*VLOOKUP($G112,'Claude Prices'!$A$5:$G$22,7,FALSE))/1000000,0) | O112: =N112*ClaudeFxRate
A113: 46121 | B113: story | C113: FAL-13 | D113: 1.3 | E113: Upload documents | F113: claude-sonnet-5 | G113: claude-sonnet-5 | H113: 20 | I113: 3833 | J113: 50000 | K113: 208333 | L113: 3341666 | M113: 50833 | N113: =IFERROR((I113*VLOOKUP($G113,'Claude Prices'!$A$5:$G$22,3,FALSE)+J113*VLOOKUP($G113,'Claude Prices'!$A$5:$G$22,4,FALSE)+K113*VLOOKUP($G113,'Claude Prices'!$A$5:$G$22,5,FALSE)+L113*VLOOKUP($G113,'Claude Prices'!$A$5:$G$22,6,FALSE)+M113*VLOOKUP($G113,'Claude Prices'!$A$5:$G$22,7,FALSE))/1000000,0) | O113: =N113*ClaudeFxRate
A114: 46121 | B114: ops | C114: merges, promotions & deploys | F114: claude-haiku-4-5-20251001 | G114: claude-haiku-4-5 | H114: 1 | I114: 294 | J114: 1294 | K114: 4941 | L114: 101176 | M114: 1117 | N114: =IFERROR((I114*VLOOKUP($G114,'Claude Prices'!$A$5:$G$22,3,FALSE)+J114*VLOOKUP($G114,'Claude Prices'!$A$5:$G$22,4,FALSE)+K114*VLOOKUP($G114,'Claude Prices'!$A$5:$G$22,5,FALSE)+L114*VLOOKUP($G114,'Claude Prices'!$A$5:$G$22,6,FALSE)+M114*VLOOKUP($G114,'Claude Prices'!$A$5:$G$22,7,FALSE))/1000000,0) | O114: =N114*ClaudeFxRate
A115: 46122 | B115: story | C115: FAL-13 | D115: 1.3 | E115: Upload documents | F115: claude-haiku-4-5-20251001 | G115: claude-haiku-4-5 | H115: 8 | I115: 1500 | J115: 7500 | K115: 25000 | L115: 516666 | M115: 5833 | N115: =IFERROR((I115*VLOOKUP($G115,'Claude Prices'!$A$5:$G$22,3,FALSE)+J115*VLOOKUP($G115,'Claude Prices'!$A$5:$G$22,4,FALSE)+K115*VLOOKUP($G115,'Claude Prices'!$A$5:$G$22,5,FALSE)+L115*VLOOKUP($G115,'Claude Prices'!$A$5:$G$22,6,FALSE)+M115*VLOOKUP($G115,'Claude Prices'!$A$5:$G$22,7,FALSE))/1000000,0) | O115: =N115*ClaudeFxRate
A116: 46122 | B116: story | C116: FAL-13 | D116: 1.3 | E116: Upload documents | F116: claude-sonnet-5 | G116: claude-sonnet-5 | H116: 20 | I116: 3833 | J116: 50000 | K116: 208333 | L116: 3341666 | M116: 50833 | N116: =IFERROR((I116*VLOOKUP($G116,'Claude Prices'!$A$5:$G$22,3,FALSE)+J116*VLOOKUP($G116,'Claude Prices'!$A$5:$G$22,4,FALSE)+K116*VLOOKUP($G116,'Claude Prices'!$A$5:$G$22,5,FALSE)+L116*VLOOKUP($G116,'Claude Prices'!$A$5:$G$22,6,FALSE)+M116*VLOOKUP($G116,'Claude Prices'!$A$5:$G$22,7,FALSE))/1000000,0) | O116: =N116*ClaudeFxRate
A117: 46122 | B117: ops | C117: merges, promotions & deploys | F117: claude-haiku-4-5-20251001 | G117: claude-haiku-4-5 | H117: 1 | I117: 294 | J117: 1294 | K117: 4941 | L117: 101176 | M117: 1117 | N117: =IFERROR((I117*VLOOKUP($G117,'Claude Prices'!$A$5:$G$22,3,FALSE)+J117*VLOOKUP($G117,'Claude Prices'!$A$5:$G$22,4,FALSE)+K117*VLOOKUP($G117,'Claude Prices'!$A$5:$G$22,5,FALSE)+L117*VLOOKUP($G117,'Claude Prices'!$A$5:$G$22,6,FALSE)+M117*VLOOKUP($G117,'Claude Prices'!$A$5:$G$22,7,FALSE))/1000000,0) | O117: =N117*ClaudeFxRate
A118: 46125 | B118: story | C118: FAL-13 | D118: 1.3 | E118: Upload documents | F118: claude-haiku-4-5-20251001 | G118: claude-haiku-4-5 | H118: 8 | I118: 1500 | J118: 7500 | K118: 25000 | L118: 516666 | M118: 5833 | N118: =IFERROR((I118*VLOOKUP($G118,'Claude Prices'!$A$5:$G$22,3,FALSE)+J118*VLOOKUP($G118,'Claude Prices'!$A$5:$G$22,4,FALSE)+K118*VLOOKUP($G118,'Claude Prices'!$A$5:$G$22,5,FALSE)+L118*VLOOKUP($G118,'Claude Prices'!$A$5:$G$22,6,FALSE)+M118*VLOOKUP($G118,'Claude Prices'!$A$5:$G$22,7,FALSE))/1000000,0) | O118: =N118*ClaudeFxRate
A119: 46125 | B119: story | C119: FAL-13 | D119: 1.3 | E119: Upload documents | F119: claude-sonnet-5 | G119: claude-sonnet-5 | H119: 20 | I119: 3833 | J119: 50000 | K119: 208333 | L119: 3341666 | M119: 50833 | N119: =IFERROR((I119*VLOOKUP($G119,'Claude Prices'!$A$5:$G$22,3,FALSE)+J119*VLOOKUP($G119,'Claude Prices'!$A$5:$G$22,4,FALSE)+K119*VLOOKUP($G119,'Claude Prices'!$A$5:$G$22,5,FALSE)+L119*VLOOKUP($G119,'Claude Prices'!$A$5:$G$22,6,FALSE)+M119*VLOOKUP($G119,'Claude Prices'!$A$5:$G$22,7,FALSE))/1000000,0) | O119: =N119*ClaudeFxRate
A120: 46125 | B120: ops | C120: merges, promotions & deploys | F120: claude-haiku-4-5-20251001 | G120: claude-haiku-4-5 | H120: 1 | I120: 294 | J120: 1294 | K120: 4941 | L120: 101176 | M120: 1117 | N120: =IFERROR((I120*VLOOKUP($G120,'Claude Prices'!$A$5:$G$22,3,FALSE)+J120*VLOOKUP($G120,'Claude Prices'!$A$5:$G$22,4,FALSE)+K120*VLOOKUP($G120,'Claude Prices'!$A$5:$G$22,5,FALSE)+L120*VLOOKUP($G120,'Claude Prices'!$A$5:$G$22,6,FALSE)+M120*VLOOKUP($G120,'Claude Prices'!$A$5:$G$22,7,FALSE))/1000000,0) | O120: =N120*ClaudeFxRate
A121: 46126 | B121: story | C121: FAL-13 | D121: 1.3 | E121: Upload documents | F121: claude-haiku-4-5-20251001 | G121: claude-haiku-4-5 | H121: 8 | I121: 1500 | J121: 7500 | K121: 25000 | L121: 516666 | M121: 5833 | N121: =IFERROR((I121*VLOOKUP($G121,'Claude Prices'!$A$5:$G$22,3,FALSE)+J121*VLOOKUP($G121,'Claude Prices'!$A$5:$G$22,4,FALSE)+K121*VLOOKUP($G121,'Claude Prices'!$A$5:$G$22,5,FALSE)+L121*VLOOKUP($G121,'Claude Prices'!$A$5:$G$22,6,FALSE)+M121*VLOOKUP($G121,'Claude Prices'!$A$5:$G$22,7,FALSE))/1000000,0) | O121: =N121*ClaudeFxRate
A122: 46126 | B122: story | C122: FAL-13 | D122: 1.3 | E122: Upload documents | F122: claude-sonnet-5 | G122: claude-sonnet-5 | H122: 20 | I122: 3833 | J122: 50000 | K122: 208333 | L122: 3341666 | M122: 50833 | N122: =IFERROR((I122*VLOOKUP($G122,'Claude Prices'!$A$5:$G$22,3,FALSE)+J122*VLOOKUP($G122,'Claude Prices'!$A$5:$G$22,4,FALSE)+K122*VLOOKUP($G122,'Claude Prices'!$A$5:$G$22,5,FALSE)+L122*VLOOKUP($G122,'Claude Prices'!$A$5:$G$22,6,FALSE)+M122*VLOOKUP($G122,'Claude Prices'!$A$5:$G$22,7,FALSE))/1000000,0) | O122: =N122*ClaudeFxRate
A123: 46126 | B123: ops | C123: merges, promotions & deploys | F123: claude-haiku-4-5-20251001 | G123: claude-haiku-4-5 | H123: 1 | I123: 294 | J123: 1294 | K123: 4941 | L123: 101176 | M123: 1117 | N123: =IFERROR((I123*VLOOKUP($G123,'Claude Prices'!$A$5:$G$22,3,FALSE)+J123*VLOOKUP($G123,'Claude Prices'!$A$5:$G$22,4,FALSE)+K123*VLOOKUP($G123,'Claude Prices'!$A$5:$G$22,5,FALSE)+L123*VLOOKUP($G123,'Claude Prices'!$A$5:$G$22,6,FALSE)+M123*VLOOKUP($G123,'Claude Prices'!$A$5:$G$22,7,FALSE))/1000000,0) | O123: =N123*ClaudeFxRate
A124: 46127 | B124: story | C124: FAL-13 | D124: 1.3 | E124: Upload documents | F124: claude-haiku-4-5-20251001 | G124: claude-haiku-4-5 | H124: 8 | I124: 1500 | J124: 7500 | K124: 25000 | L124: 516666 | M124: 5833 | N124: =IFERROR((I124*VLOOKUP($G124,'Claude Prices'!$A$5:$G$22,3,FALSE)+J124*VLOOKUP($G124,'Claude Prices'!$A$5:$G$22,4,FALSE)+K124*VLOOKUP($G124,'Claude Prices'!$A$5:$G$22,5,FALSE)+L124*VLOOKUP($G124,'Claude Prices'!$A$5:$G$22,6,FALSE)+M124*VLOOKUP($G124,'Claude Prices'!$A$5:$G$22,7,FALSE))/1000000,0) | O124: =N124*ClaudeFxRate
A125: 46127 | B125: story | C125: FAL-13 | D125: 1.3 | E125: Upload documents | F125: claude-sonnet-5 | G125: claude-sonnet-5 | H125: 20 | I125: 3833 | J125: 50000 | K125: 208333 | L125: 3341666 | M125: 50833 | N125: =IFERROR((I125*VLOOKUP($G125,'Claude Prices'!$A$5:$G$22,3,FALSE)+J125*VLOOKUP($G125,'Claude Prices'!$A$5:$G$22,4,FALSE)+K125*VLOOKUP($G125,'Claude Prices'!$A$5:$G$22,5,FALSE)+L125*VLOOKUP($G125,'Claude Prices'!$A$5:$G$22,6,FALSE)+M125*VLOOKUP($G125,'Claude Prices'!$A$5:$G$22,7,FALSE))/1000000,0) | O125: =N125*ClaudeFxRate
A126: 46127 | B126: ops | C126: merges, promotions & deploys | F126: claude-haiku-4-5-20251001 | G126: claude-haiku-4-5 | H126: 1 | I126: 294 | J126: 1294 | K126: 4941 | L126: 101176 | M126: 1117 | N126: =IFERROR((I126*VLOOKUP($G126,'Claude Prices'!$A$5:$G$22,3,FALSE)+J126*VLOOKUP($G126,'Claude Prices'!$A$5:$G$22,4,FALSE)+K126*VLOOKUP($G126,'Claude Prices'!$A$5:$G$22,5,FALSE)+L126*VLOOKUP($G126,'Claude Prices'!$A$5:$G$22,6,FALSE)+M126*VLOOKUP($G126,'Claude Prices'!$A$5:$G$22,7,FALSE))/1000000,0) | O126: =N126*ClaudeFxRate
A127: 46128 | B127: story | C127: FAL-13 | D127: 1.3 | E127: Upload documents | F127: claude-haiku-4-5-20251001 | G127: claude-haiku-4-5 | H127: 8 | I127: 1500 | J127: 7500 | K127: 25000 | L127: 516666 | M127: 5833 | N127: =IFERROR((I127*VLOOKUP($G127,'Claude Prices'!$A$5:$G$22,3,FALSE)+J127*VLOOKUP($G127,'Claude Prices'!$A$5:$G$22,4,FALSE)+K127*VLOOKUP($G127,'Claude Prices'!$A$5:$G$22,5,FALSE)+L127*VLOOKUP($G127,'Claude Prices'!$A$5:$G$22,6,FALSE)+M127*VLOOKUP($G127,'Claude Prices'!$A$5:$G$22,7,FALSE))/1000000,0) | O127: =N127*ClaudeFxRate
A128: 46128 | B128: story | C128: FAL-13 | D128: 1.3 | E128: Upload documents | F128: claude-sonnet-5 | G128: claude-sonnet-5 | H128: 20 | I128: 3833 | J128: 50000 | K128: 208333 | L128: 3341666 | M128: 50833 | N128: =IFERROR((I128*VLOOKUP($G128,'Claude Prices'!$A$5:$G$22,3,FALSE)+J128*VLOOKUP($G128,'Claude Prices'!$A$5:$G$22,4,FALSE)+K128*VLOOKUP($G128,'Claude Prices'!$A$5:$G$22,5,FALSE)+L128*VLOOKUP($G128,'Claude Prices'!$A$5:$G$22,6,FALSE)+M128*VLOOKUP($G128,'Claude Prices'!$A$5:$G$22,7,FALSE))/1000000,0) | O128: =N128*ClaudeFxRate
A129: 46128 | B129: ops | C129: merges, promotions & deploys | F129: claude-haiku-4-5-20251001 | G129: claude-haiku-4-5 | H129: 1 | I129: 294 | J129: 1294 | K129: 4941 | L129: 101176 | M129: 1117 | N129: =IFERROR((I129*VLOOKUP($G129,'Claude Prices'!$A$5:$G$22,3,FALSE)+J129*VLOOKUP($G129,'Claude Prices'!$A$5:$G$22,4,FALSE)+K129*VLOOKUP($G129,'Claude Prices'!$A$5:$G$22,5,FALSE)+L129*VLOOKUP($G129,'Claude Prices'!$A$5:$G$22,6,FALSE)+M129*VLOOKUP($G129,'Claude Prices'!$A$5:$G$22,7,FALSE))/1000000,0) | O129: =N129*ClaudeFxRate
A130: 46129 | B130: story | C130: FAL-13 | D130: 1.3 | E130: Upload documents | F130: claude-haiku-4-5-20251001 | G130: claude-haiku-4-5 | H130: 8 | I130: 1500 | J130: 7500 | K130: 25000 | L130: 516666 | M130: 5833 | N130: =IFERROR((I130*VLOOKUP($G130,'Claude Prices'!$A$5:$G$22,3,FALSE)+J130*VLOOKUP($G130,'Claude Prices'!$A$5:$G$22,4,FALSE)+K130*VLOOKUP($G130,'Claude Prices'!$A$5:$G$22,5,FALSE)+L130*VLOOKUP($G130,'Claude Prices'!$A$5:$G$22,6,FALSE)+M130*VLOOKUP($G130,'Claude Prices'!$A$5:$G$22,7,FALSE))/1000000,0) | O130: =N130*ClaudeFxRate
A131: 46129 | B131: story | C131: FAL-13 | D131: 1.3 | E131: Upload documents | F131: claude-sonnet-5 | G131: claude-sonnet-5 | H131: 20 | I131: 3833 | J131: 50000 | K131: 208333 | L131: 3341666 | M131: 50833 | N131: =IFERROR((I131*VLOOKUP($G131,'Claude Prices'!$A$5:$G$22,3,FALSE)+J131*VLOOKUP($G131,'Claude Prices'!$A$5:$G$22,4,FALSE)+K131*VLOOKUP($G131,'Claude Prices'!$A$5:$G$22,5,FALSE)+L131*VLOOKUP($G131,'Claude Prices'!$A$5:$G$22,6,FALSE)+M131*VLOOKUP($G131,'Claude Prices'!$A$5:$G$22,7,FALSE))/1000000,0) | O131: =N131*ClaudeFxRate
A132: 46129 | B132: ops | C132: merges, promotions & deploys | F132: claude-haiku-4-5-20251001 | G132: claude-haiku-4-5 | H132: 1 | I132: 294 | J132: 1294 | K132: 4941 | L132: 101176 | M132: 1117 | N132: =IFERROR((I132*VLOOKUP($G132,'Claude Prices'!$A$5:$G$22,3,FALSE)+J132*VLOOKUP($G132,'Claude Prices'!$A$5:$G$22,4,FALSE)+K132*VLOOKUP($G132,'Claude Prices'!$A$5:$G$22,5,FALSE)+L132*VLOOKUP($G132,'Claude Prices'!$A$5:$G$22,6,FALSE)+M132*VLOOKUP($G132,'Claude Prices'!$A$5:$G$22,7,FALSE))/1000000,0) | O132: =N132*ClaudeFxRate
A133: 46132 | B133: story | C133: FAL-13 | D133: 1.3 | E133: Upload documents | F133: claude-haiku-4-5-20251001 | G133: claude-haiku-4-5 | H133: 8 | I133: 1500 | J133: 7500 | K133: 25000 | L133: 516674 | M133: 5837 | N133: =IFERROR((I133*VLOOKUP($G133,'Claude Prices'!$A$5:$G$22,3,FALSE)+J133*VLOOKUP($G133,'Claude Prices'!$A$5:$G$22,4,FALSE)+K133*VLOOKUP($G133,'Claude Prices'!$A$5:$G$22,5,FALSE)+L133*VLOOKUP($G133,'Claude Prices'!$A$5:$G$22,6,FALSE)+M133*VLOOKUP($G133,'Claude Prices'!$A$5:$G$22,7,FALSE))/1000000,0) | O133: =N133*ClaudeFxRate
A134: 46132 | B134: story | C134: FAL-13 | D134: 1.3 | E134: Upload documents | F134: claude-sonnet-5 | G134: claude-sonnet-5 | H134: 28 | I134: 3837 | J134: 50000 | K134: 208337 | L134: 3341674 | M134: 50837 | N134: =IFERROR((I134*VLOOKUP($G134,'Claude Prices'!$A$5:$G$22,3,FALSE)+J134*VLOOKUP($G134,'Claude Prices'!$A$5:$G$22,4,FALSE)+K134*VLOOKUP($G134,'Claude Prices'!$A$5:$G$22,5,FALSE)+L134*VLOOKUP($G134,'Claude Prices'!$A$5:$G$22,6,FALSE)+M134*VLOOKUP($G134,'Claude Prices'!$A$5:$G$22,7,FALSE))/1000000,0) | O134: =N134*ClaudeFxRate
A135: 46132 | B135: ops | C135: merges, promotions & deploys | F135: claude-haiku-4-5-20251001 | G135: claude-haiku-4-5 | H135: 1 | I135: 294 | J135: 1294 | K135: 4941 | L135: 101176 | M135: 1117 | N135: =IFERROR((I135*VLOOKUP($G135,'Claude Prices'!$A$5:$G$22,3,FALSE)+J135*VLOOKUP($G135,'Claude Prices'!$A$5:$G$22,4,FALSE)+K135*VLOOKUP($G135,'Claude Prices'!$A$5:$G$22,5,FALSE)+L135*VLOOKUP($G135,'Claude Prices'!$A$5:$G$22,6,FALSE)+M135*VLOOKUP($G135,'Claude Prices'!$A$5:$G$22,7,FALSE))/1000000,0) | O135: =N135*ClaudeFxRate
...

Sheet Project Timeline
A1: Project timeline
A2: Started 2026-01-05; completed 2026-06-26; 173 calendar days, 125 working days. From git history of the BMad artifacts and sprint status, the agents' sanctums and the token ledger.
A4: Category | B4: Name | C4: Detail | D4: Status | E4: Started | F4: Completed | G4: Days | H4: Source
A5: project | B5: falcon-portal | C5: 125 working days | D5: complete | E5: 46027 | F5: 46199 | G5: 173 | H5: summary
A6: bmad stage | B6: spec / PRD | C6: _bmad-output/specs/SPEC.md | E6: 46028 | F6: 46030 | G6: 3 | H6: git
A7: bmad stage | B7: architecture | C7: _bmad-output/planning-artifacts/architecture/falcon/ARCHITECTURE-SPINE.md | E7: 46034 | F7: 46044 | G7: 11 | H7: git
A8: bmad stage | B8: UX design | C8: _bmad-output/planning-artifacts/ux-design.md | E8: 46041 | F8: 46045 | G8: 5 | H8: git
A9: bmad stage | B9: epics & stories | C9: _bmad-output/planning-artifacts/epics.md | E9: 46048 | F9: 46049 | G9: 2 | H9: git
A10: bmad stage | B10: sprint status | C10: _bmad-output/implementation-artifacts/sprint-status.yaml | E10: 46083 | F10: 46199 | G10: 117 | H10: git
A11: agent | B11: agent-jules | C11: 6 session logs | E11: 46042 | F11: 46073 | G11: 32 | H11: sanctum
A12: agent | B12: agent-scrooge | C12: 4 session logs | E12: 46042 | F12: 46199 | G12: 158 | H12: sanctum
A13: epic | B13: epic-1 | C13: 3 stories | D13: done | E13: 46083 | F13: 46132 | G13: 50 | H13: git
A14: story | B14: 1-1-sign-in | C14: epic-1 | D14: done | E14: 46083 | F14: 46098 | G14: 16 | H14: git
A15: story | B15: 1-2-start-application | C15: epic-1 | D15: done | E15: 46099 | F15: 46114 | G15: 16 | H15: git
A16: story | B16: 1-3-upload-documents | C16: epic-1 | D16: done | E16: 46115 | F16: 46132 | G16: 18 | H16: git
A17: epic | B17: epic-2 | C17: 3 stories | D17: done | E17: 46133 | F17: 46199 | G17: 67 | H17: git
A18: story | B18: 2-1-review-queue | C18: epic-2 | D18: done | E18: 46133 | F18: 46154 | G18: 22 | H18: git
A19: story | B19: 2-2-approve-or-reject | C19: epic-2 | D19: done | E19: 46155 | F19: 46176 | G19: 22 | H19: git
A20: story | B20: 2-3-notify-customer | C20: epic-2 | D20: done | E20: 46177 | F20: 46199 | G20: 23 | H20: git

Sheet Sources & Gaps
A1: Sources, assumptions and gaps
A3: Price basis
B4: Azure Retail Prices API list prices (pay-as-you-go, no discounts), region uaenorth, USD, fetched 2026-09-28.
B5: Rate card: Synthetic sample rates, not a real rate card, updated 2026-09-28.
B6: Claude API list prices from https://platform.claude.com/docs/en/about-claude/pricing, read 2026-09-28, USD per million tokens. Claude Code on a subscription is billed per seat: this is the API-equivalent cost.
B7: Horizon: 5 years of run after go-live, run costs rising 3% a year.
A9: Gaps: not priced and not in any total
B10: Disaster recovery: the spine does not say whether Prod has a second region.
B11: Azure SQL backup retention beyond the default is not stated.
A13: Assumptions and owner statements (not from the BMad artifacts)
B14: Dev / Document storage: assumption: 50 GB of test documents
B15: Test / Document storage: assumption: 50 GB of test documents
B16: Team / Project Manager: owner: Delivery Manager, 2026-09-28
B17: Team / Solution Architect: owner: Delivery Manager, 2026-09-28
B18: Team / QA Engineer: owner: Delivery Manager, 2026-09-28
B19: Other / Penetration test: owner: Security Lead, 2026-09-28
B20: Other / GitHub Enterprise seats (12 months): assumption: 7 seats at list price
B21: Run cost / Azure support plan (Standard): assumption: Standard support at list price
B22: Run cost / GitHub Enterprise seats (4 for support): assumption: 4 seats at list price
B23: Support / Developer: owner: Delivery Manager, 2026-09-28
B24: Support / DevOps Engineer: owner: Delivery Manager, 2026-09-28
B25: Support / QA Engineer: owner: Delivery Manager, 2026-09-28
... B28: Phase budget / test design: owner: Delivery Manager (synthetic), 2026-09-28
A30: Stamp: built 2026-09-28T15:18:38; sha256 of each cited file
B31: _bmad-output/planning-artifacts/architecture/falcon/ARCHITECTURE-SPINE.md 888bd47cdcac
B32: _bmad-output/planning-artifacts/epics.md 68f432fd10b0
B33: _bmad-output/specs/SPEC.md 13119f5f0756
B34: token_usage/claude_usage.csv e972364ca316
B35: claude-prices.json 0dcde61aa110
B36: token_usage/project_timeline.csv 08bf946524c1
B37: token_usage/claude_usage_daily.csv 2a1ddfa62ec0
